{
  "screener_results": [
    {
      "symbol": "UPS",
      "name": "United Parcel Service, Inc.",
      "sector": "Industrials",
      "industry": "Integrated Freight & Logistics",
      "price": 97.61,
      "market_cap": 82940821504,
      "fundamentals": {
        "trailing_pe": 14.88,
        "forward_pe": 12.25,
        "pb_ratio": 5.11,
        "ps_ratio": 0.94,
        "ev_ebitda": 8.67,
        "earnings_yield": 6.72,
        "revenue_growth": -3.2,
        "earnings_growth": 4.6,
        "growth_tier": "stable"
      },
      "technicals": {
        "sma_50": 106.6,
        "sma_200": 94.83,
        "rsi": 51.55,
        "week_52_high": 122.41,
        "week_52_low": 82.0,
        "bollinger_position": 45.36,
        "price_vs_sma50": -8.43,
        "price_vs_sma200": 2.93
      },
      "scores": {
        "per_score": 80.0,
        "pbr_score": 10,
        "psr_score": 100,
        "ev_ebitda_score": 60,
        "earnings_yield_score": 60,
        "fundamental_score": 62.0,
        "technical_score": 63.1,
        "value_score": 62.33
      },
      "grade": "B+",
      "recommendation": "Moderate Buy",
      "fetched_at": "2026-04-02T14:53:08.458115"
    },
    {
      "symbol": "DIS",
      "name": "Walt Disney Company (The)",
      "sector": "Communication Services",
      "industry": "Entertainment",
      "price": 96.52,
      "market_cap": 171167301632,
      "fundamentals": {
        "trailing_pe": 14.22,
        "forward_pe": 13.15,
        "pb_ratio": 1.58,
        "ps_ratio": 1.79,
        "ev_ebitda": 11.27,
        "earnings_yield": 7.03,
        "revenue_growth": 5.2,
        "earnings_growth": -4.3,
        "growth_tier": "stable"
      },
      "technicals": {
        "sma_50": 103.38,
        "sma_200": 111.03,
        "rsi": 40.74,
        "week_52_high": 124.69,
        "week_52_low": 80.1,
        "bollinger_position": 34.23,
        "price_vs_sma50": -6.64,
        "price_vs_sma200": -13.07
      },
      "scores": {
        "per_score": 80.0,
        "pbr_score": 60,
        "psr_score": 80,
        "ev_ebitda_score": 40,
        "earnings_yield_score": 60,
        "fundamental_score": 65.0,
        "technical_score": 50.78,
        "value_score": 60.73
      },
      "grade": "B+",
      "recommendation": "Moderate Buy",
      "fetched_at": "2026-04-02T14:53:05.980587"
    },
    {
      "symbol": "PSX",
      "name": "Phillips 66",
      "sector": "Energy",
      "industry": "Oil & Gas Refining & Marketing",
      "price": 177.57,
      "market_cap": 71160119296,
      "fundamentals": {
        "trailing_pe": 16.47,
        "forward_pe": 12.3,
        "pb_ratio": 2.45,
        "ps_ratio": 0.54,
        "ev_ebitda": 13.79,
        "earnings_yield": 6.07,
        "revenue_growth": 1.3,
        "earnings_growth": 242728.4,
        "growth_tier": "hypergrowth"
      },
      "technicals": {
        "sma_50": 161.57,
        "sma_200": 137.33,
        "rsi": 55.61,
        "week_52_high": 190.61,
        "week_52_low": 91.01,
        "bollinger_position": 56.5,
        "price_vs_sma50": 9.91,
        "price_vs_sma200": 29.3
      },
      "scores": {
        "per_score": 74.0,
        "pbr_score": 40,
        "psr_score": 100,
        "ev_ebitda_score": 40,
        "earnings_yield_score": 60,
        "fundamental_score": 62.2,
        "technical_score": 49.41,
        "value_score": 58.36
      },
      "grade": "B",
      "recommendation": "Hold",
      "fetched_at": "2026-04-02T14:53:12.530981"
    },
    {
      "symbol": "BMY",
      "name": "Bristol-Myers Squibb Company",
      "sector": "Healthcare",
      "industry": "Drug Manufacturers - General",
      "price": 60.32,
      "market_cap": 123157479424,
      "fundamentals": {
        "trailing_pe": 17.43,
        "forward_pe": 9.82,
        "pb_ratio": 6.65,
        "ps_ratio": 2.56,
        "ev_ebitda": 8.49,
        "earnings_yield": 5.74,
        "revenue_growth": 1.3,
        "earnings_growth": 1392.1,
        "growth_tier": "hypergrowth"
      },
      "technicals": {
        "sma_50": 59.19,
        "sma_200": 50.19,
        "rsi": 55.51,
        "week_52_high": 62.89,
        "week_52_low": 42.52,
        "bollinger_position": 70.43,
        "price_vs_sma50": 1.91,
        "price_vs_sma200": 20.19
      },
      "scores": {
        "per_score": 88.0,
        "pbr_score": 10,
        "psr_score": 60,
        "ev_ebitda_score": 60,
        "earnings_yield_score": 60,
        "fundamental_score": 58.4,
        "technical_score": 46.98,
        "value_score": 54.97
      },
      "grade": "B",
      "recommendation": "Hold",
      "fetched_at": "2026-04-02T14:53:01.847051"
    },
    {
      "symbol": "BAC",
      "name": "Bank of America Corporation",
      "sector": "Financial Services",
      "industry": "Banks - Diversified",
      "price": 49.03,
      "market_cap": 351836831744,
      "fundamentals": {
        "trailing_pe": 12.87,
        "forward_pe": 9.87,
        "pb_ratio": 1.28,
        "ps_ratio": 3.28,
        "ev_ebitda": 0,
        "earnings_yield": 7.77,
        "revenue_growth": 7.2,
        "earnings_growth": 21.2,
        "growth_tier": "moderate_growth"
      },
      "technicals": {
        "sma_50": 50.55,
        "sma_200": 50.36,
        "rsi": 65.89,
        "week_52_high": 57.55,
        "week_52_low": 33.07,
        "bollinger_position": 86.8,
        "price_vs_sma50": -3.01,
        "price_vs_sma200": -2.64
      },
      "scores": {
        "per_score": 90.0,
        "pbr_score": 80,
        "psr_score": 40,
        "ev_ebitda_score": 0,
        "earnings_yield_score": 80,
        "fundamental_score": 61.0,
        "technical_score": 40.1,
        "value_score": 54.73
      },
      "grade": "B",
      "recommendation": "Hold",
      "fetched_at": "2026-04-02T14:52:55.075688"
    },
    {
      "symbol": "EOG",
      "name": "EOG Resources, Inc.",
      "sector": "Energy",
      "industry": "Oil & Gas E&P",
      "price": 142.16,
      "market_cap": 76267634688,
      "fundamentals": {
        "trailing_pe": 15.6,
        "forward_pe": 11.43,
        "pb_ratio": 2.56,
        "ps_ratio": 3.37,
        "ev_ebitda": 6.92,
        "earnings_yield": 6.41,
        "revenue_growth": 0,
        "earnings_growth": -41.7,
        "growth_tier": "declining"
      },
      "technicals": {
        "sma_50": 126.05,
        "sma_200": 115.09,
        "rsi": 65.46,
        "week_52_high": 151.87,
        "week_52_low": 101.59,
        "bollinger_position": 63.94,
        "price_vs_sma50": 12.78,
        "price_vs_sma200": 23.52
      },
      "scores": {
        "per_score": 66.0,
        "pbr_score": 40,
        "psr_score": 40,
        "ev_ebitda_score": 80,
        "earnings_yield_score": 60,
        "fundamental_score": 58.8,
        "technical_score": 42.38,
        "value_score": 53.87
      },
      "grade": "B",
      "recommendation": "Hold",
      "fetched_at": "2026-04-02T14:53:12.243435"
    },
    {
      "symbol": "UNH",
      "name": "UnitedHealth Group Incorporated",
      "sector": "Healthcare",
      "industry": "Healthcare Plans",
      "price": 276.76,
      "market_cap": 251208368128,
      "fundamentals": {
        "trailing_pe": 20.92,
        "forward_pe": 13.82,
        "pb_ratio": 2.66,
        "ps_ratio": 0.56,
        "ev_ebitda": 14.39,
        "earnings_yield": 4.78,
        "revenue_growth": 12.3,
        "earnings_growth": -99.9,
        "growth_tier": "declining"
      },
      "technicals": {
        "sma_50": 284.43,
        "sma_200": 308.53,
        "rsi": 45.34,
        "week_52_high": 606.36,
        "week_52_low": 234.6,
        "bollinger_position": 50.47,
        "price_vs_sma50": -2.7,
        "price_vs_sma200": -10.3
      },
      "scores": {
        "per_score": 52.0,
        "pbr_score": 40,
        "psr_score": 100,
        "ev_ebitda_score": 40,
        "earnings_yield_score": 40,
        "fundamental_score": 52.6,
        "technical_score": 53.05,
        "value_score": 52.74
      },
      "grade": "B",
      "recommendation": "Hold",
      "fetched_at": "2026-04-02T14:52:58.914822"
    },
    {
      "symbol": "MPC",
      "name": "Marathon Petroleum Corporation",
      "sector": "Energy",
      "industry": "Oil & Gas Refining & Marketing",
      "price": 242.34,
      "market_cap": 71427325952,
      "fundamentals": {
        "trailing_pe": 18.33,
        "forward_pe": 13.19,
        "pb_ratio": 4.13,
        "ps_ratio": 0.54,
        "ev_ebitda": 11.37,
        "earnings_yield": 5.46,
        "revenue_growth": -1.2,
        "earnings_growth": 350.7,
        "growth_tier": "hypergrowth"
      },
      "technicals": {
        "sma_50": 210.12,
        "sma_200": 186.16,
        "rsi": 64.33,
        "week_52_high": 255.77,
        "week_52_low": 115.1,
        "bollinger_position": 69.62,
        "price_vs_sma50": 15.33,
        "price_vs_sma200": 30.18
      },
      "scores": {
        "per_score": 74.0,
        "pbr_score": 20,
        "psr_score": 100,
        "ev_ebitda_score": 40,
        "earnings_yield_score": 40,
        "fundamental_score": 55.2,
        "technical_score": 43.22,
        "value_score": 51.61
      },
      "grade": "B",
      "recommendation": "Hold",
      "fetched_at": "2026-04-02T14:53:13.219732"
    },
    {
      "symbol": "WFC",
      "name": "Wells Fargo & Company",
      "sector": "Financial Services",
      "industry": "Banks - Diversified",
      "price": 80.08,
      "market_cap": 247097704448,
      "fundamentals": {
        "trailing_pe": 12.79,
        "forward_pe": 10.1,
        "pb_ratio": 1.51,
        "ps_ratio": 3.09,
        "ev_ebitda": 0,
        "earnings_yield": 7.82,
        "revenue_growth": 5.0,
        "earnings_growth": 13.1,
        "growth_tier": "moderate_growth"
      },
      "technicals": {
        "sma_50": 83.87,
        "sma_200": 83.58,
        "rsi": 71.42,
        "week_52_high": 97.76,
        "week_52_low": 58.42,
        "bollinger_position": 79.78,
        "price_vs_sma50": -4.52,
        "price_vs_sma200": -4.19
      },
      "scores": {
        "per_score": 80.0,
        "pbr_score": 60,
        "psr_score": 40,
        "ev_ebitda_score": 0,
        "earnings_yield_score": 80,
        "fundamental_score": 54.0,
        "technical_score": 45.09,
        "value_score": 51.33
      },
      "grade": "B",
      "recommendation": "Hold",
      "fetched_at": "2026-04-02T14:52:55.614528"
    },
    {
      "symbol": "COP",
      "name": "ConocoPhillips",
      "sector": "Energy",
      "industry": "Oil & Gas E&P",
      "price": 130.07,
      "market_cap": 158977425408,
      "fundamentals": {
        "trailing_pe": 20.48,
        "forward_pe": 18.07,
        "pb_ratio": 2.47,
        "ps_ratio": 2.64,
        "ev_ebitda": 7.22,
        "earnings_yield": 4.88,
        "revenue_growth": -6.8,
        "earnings_growth": -39.0,
        "growth_tier": "declining"
      },
      "technicals": {
        "sma_50": 114.67,
        "sma_200": 97.17,
        "rsi": 69.48,
        "week_52_high": 135.87,
        "week_52_low": 79.88,
        "bollinger_position": 70.61,
        "price_vs_sma50": 13.43,
        "price_vs_sma200": 33.86
      },
      "scores": {
        "per_score": 46.0,
        "pbr_score": 40,
        "psr_score": 60,
        "ev_ebitda_score": 80,
        "earnings_yield_score": 40,
        "fundamental_score": 52.8,
        "technical_score": 44.5,
        "value_score": 50.31
      },
      "grade": "B",
      "recommendation": "Hold",
      "fetched_at": "2026-04-02T14:53:11.480935"
    },
    {
      "symbol": "C",
      "name": "Citigroup, Inc.",
      "sector": "Financial Services",
      "industry": "Banks - Diversified",
      "price": 114.51,
      "market_cap": 200297037824,
      "fundamentals": {
        "trailing_pe": 16.38,
        "forward_pe": 9.43,
        "pb_ratio": 1.04,
        "ps_ratio": 2.65,
        "ev_ebitda": 0,
        "earnings_yield": 6.1,
        "revenue_growth": 4.4,
        "earnings_growth": -10.8,
        "growth_tier": "declining"
      },
      "technicals": {
        "sma_50": 112.71,
        "sma_200": 102.36,
        "rsi": 67.31,
        "week_52_high": 125.16,
        "week_52_low": 55.51,
        "bollinger_position": 87.87,
        "price_vs_sma50": 1.59,
        "price_vs_sma200": 11.86
      },
      "scores": {
        "per_score": 72.0,
        "pbr_score": 80,
        "psr_score": 60,
        "ev_ebitda_score": 0,
        "earnings_yield_score": 60,
        "fundamental_score": 55.6,
        "technical_score": 37.53,
        "value_score": 50.18
      },
      "grade": "B",
      "recommendation": "Hold",
      "fetched_at": "2026-04-02T14:52:58.019660"
    },
    {
      "symbol": "PG",
      "name": "Procter & Gamble Company (The)",
      "sector": "Consumer Defensive",
      "industry": "Household & Personal Products",
      "price": 143.48,
      "market_cap": 335274508288,
      "fundamentals": {
        "trailing_pe": 21.29,
        "forward_pe": 19.6,
        "pb_ratio": 6.38,
        "ps_ratio": 3.93,
        "ev_ebitda": 14.61,
        "earnings_yield": 4.7,
        "revenue_growth": 1.5,
        "earnings_growth": -5.4,
        "growth_tier": "declining"
      },
      "technicals": {
        "sma_50": 153.49,
        "sma_200": 150.61,
        "rsi": 27.91,
        "week_52_high": 174.8,
        "week_52_low": 137.62,
        "bollinger_position": 27.48,
        "price_vs_sma50": -6.52,
        "price_vs_sma200": -4.73
      },
      "scores": {
        "per_score": 46.0,
        "pbr_score": 10,
        "psr_score": 40,
        "ev_ebitda_score": 40,
        "earnings_yield_score": 40,
        "fundamental_score": 35.8,
        "technical_score": 77.98,
        "value_score": 48.45
      },
      "grade": "C",
      "recommendation": "Weak Hold",
      "fetched_at": "2026-04-02T14:53:02.432362"
    },
    {
      "symbol": "SLB",
      "name": "SLB Limited",
      "sector": "Energy",
      "industry": "Oil & Gas Equipment & Services",
      "price": 49.79,
      "market_cap": 74741432320,
      "fundamentals": {
        "trailing_pe": 21.19,
        "forward_pe": 14.99,
        "pb_ratio": 2.85,
        "ps_ratio": 2.09,
        "ev_ebitda": 10.89,
        "earnings_yield": 4.72,
        "revenue_growth": 5.0,
        "earnings_growth": -28.6,
        "growth_tier": "declining"
      },
      "technicals": {
        "sma_50": 49.41,
        "sma_200": 39.18,
        "rsi": 65.37,
        "week_52_high": 54.8,
        "week_52_low": 31.11,
        "bollinger_position": 61.7,
        "price_vs_sma50": 0.77,
        "price_vs_sma200": 27.09
      },
      "scores": {
        "per_score": 52.0,
        "pbr_score": 40,
        "psr_score": 60,
        "ev_ebitda_score": 40,
        "earnings_yield_score": 40,
        "fundamental_score": 46.6,
        "technical_score": 51.53,
        "value_score": 48.08
      },
      "grade": "C",
      "recommendation": "Weak Hold",
      "fetched_at": "2026-04-02T14:53:11.833966"
    },
    {
      "symbol": "PFE",
      "name": "Pfizer, Inc.",
      "sector": "Healthcare",
      "industry": "Drug Manufacturers - General",
      "price": 28.66,
      "market_cap": 162999861248,
      "fundamentals": {
        "trailing_pe": 21.07,
        "forward_pe": 10.15,
        "pb_ratio": 1.88,
        "ps_ratio": 2.6,
        "ev_ebitda": 8.43,
        "earnings_yield": 4.75,
        "revenue_growth": -1.2,
        "earnings_growth": 0,
        "growth_tier": "declining"
      },
      "technicals": {
        "sma_50": 27.0,
        "sma_200": 24.89,
        "rsi": 72.19,
        "week_52_high": 28.75,
        "week_52_low": 20.92,
        "bollinger_position": 100,
        "price_vs_sma50": 6.13,
        "price_vs_sma200": 15.15
      },
      "scores": {
        "per_score": 52.0,
        "pbr_score": 60,
        "psr_score": 60,
        "ev_ebitda_score": 60,
        "earnings_yield_score": 40,
        "fundamental_score": 54.6,
        "technical_score": 32.12,
        "value_score": 47.86
      },
      "grade": "C",
      "recommendation": "Weak Hold",
      "fetched_at": "2026-04-02T14:52:59.331927"
    },
    {
      "symbol": "CRM",
      "name": "Salesforce, Inc.",
      "sector": "Technology",
      "industry": "Software - Application",
      "price": 185.76,
      "market_cap": 174057111552,
      "fundamentals": {
        "trailing_pe": 23.82,
        "forward_pe": 12.48,
        "pb_ratio": 2.92,
        "ps_ratio": 4.19,
        "ev_ebitda": 14.35,
        "earnings_yield": 4.2,
        "revenue_growth": 12.1,
        "earnings_growth": 17.9,
        "growth_tier": "high_growth"
      },
      "technicals": {
        "sma_50": 196.18,
        "sma_200": 236.89,
        "rsi": 41.63,
        "week_52_high": 296.05,
        "week_52_low": 174.57,
        "bollinger_position": 27.85,
        "price_vs_sma50": -5.31,
        "price_vs_sma200": -21.58
      },
      "scores": {
        "per_score": 64.0,
        "pbr_score": 40,
        "psr_score": 40,
        "ev_ebitda_score": 40,
        "earnings_yield_score": 20,
        "fundamental_score": 44.2,
        "technical_score": 53.2,
        "value_score": 46.9
      },
      "grade": "C",
      "recommendation": "Weak Hold",
      "fetched_at": "2026-04-02T14:52:54.207933"
    },
    {
      "symbol": "NKE",
      "name": "Nike, Inc.",
      "sector": "Consumer Cyclical",
      "industry": "Footwear & Accessories",
      "price": 43.7,
      "market_cap": 64692752384,
      "fundamentals": {
        "trailing_pe": 28.75,
        "forward_pe": 22.48,
        "pb_ratio": 4.59,
        "ps_ratio": 1.39,
        "ev_ebitda": 19.78,
        "earnings_yield": 3.48,
        "revenue_growth": 0.1,
        "earnings_growth": -34.8,
        "growth_tier": "declining"
      },
      "technicals": {
        "sma_50": 58.66,
        "sma_200": 65.73,
        "rsi": 21.38,
        "week_52_high": 80.17,
        "week_52_low": 43.17,
        "bollinger_position": 0,
        "price_vs_sma50": -25.51,
        "price_vs_sma200": -33.52
      },
      "scores": {
        "per_score": 40.0,
        "pbr_score": 20,
        "psr_score": 80,
        "ev_ebitda_score": 20,
        "earnings_yield_score": 20,
        "fundamental_score": 35.0,
        "technical_score": 69.81,
        "value_score": 45.44
      },
      "grade": "C",
      "recommendation": "Weak Hold",
      "fetched_at": "2026-04-02T14:53:05.336238"
    },
    {
      "symbol": "VLO",
      "name": "Valero Energy Corporation",
      "sector": "Energy",
      "industry": "Oil & Gas Refining & Marketing",
      "price": 244.33,
      "market_cap": 73061081088,
      "fundamentals": {
        "trailing_pe": 32.23,
        "forward_pe": 15.43,
        "pb_ratio": 3.08,
        "ps_ratio": 0.63,
        "ev_ebitda": 10.8,
        "earnings_yield": 3.1,
        "revenue_growth": -2.1,
        "earnings_growth": 317.9,
        "growth_tier": "hypergrowth"
      },
      "technicals": {
        "sma_50": 213.53,
        "sma_200": 171.95,
        "rsi": 60.86,
        "week_52_high": 258.43,
        "week_52_low": 99.0,
        "bollinger_position": 68.22,
        "price_vs_sma50": 14.42,
        "price_vs_sma200": 42.1
      },
      "scores": {
        "per_score": 48.0,
        "pbr_score": 20,
        "psr_score": 100,
        "ev_ebitda_score": 40,
        "earnings_yield_score": 20,
        "fundamental_score": 44.4,
        "technical_score": 46.05,
        "value_score": 44.9
      },
      "grade": "C",
      "recommendation": "Weak Hold",
      "fetched_at": "2026-04-02T14:53:12.956835"
    },
    {
      "symbol": "XOM",
      "name": "Exxon Mobil Corporation",
      "sector": "Energy",
      "industry": "Oil & Gas Integrated",
      "price": 160.76,
      "market_cap": 669869735936,
      "fundamentals": {
        "trailing_pe": 23.99,
        "forward_pe": 17.1,
        "pb_ratio": 2.59,
        "ps_ratio": 2.07,
        "ev_ebitda": 12.07,
        "earnings_yield": 4.17,
        "revenue_growth": -1.3,
        "earnings_growth": -11.0,
        "growth_tier": "declining"
      },
      "technicals": {
        "sma_50": 151.41,
        "sma_200": 122.44,
        "rsi": 57.09,
        "week_52_high": 176.41,
        "week_52_low": 97.8,
        "bollinger_position": 54.54,
        "price_vs_sma50": 6.18,
        "price_vs_sma200": 31.3
      },
      "scores": {
        "per_score": 46.0,
        "pbr_score": 40,
        "psr_score": 60,
        "ev_ebitda_score": 40,
        "earnings_yield_score": 20,
        "fundamental_score": 41.8,
        "technical_score": 50.91,
        "value_score": 44.53
      },
      "grade": "C",
      "recommendation": "Weak Hold",
      "fetched_at": "2026-04-02T14:53:10.599712"
    },
    {
      "symbol": "PEP",
      "name": "Pepsico, Inc.",
      "sector": "Consumer Defensive",
      "industry": "Beverages - Non-Alcoholic",
      "price": 155.36,
      "market_cap": 212367949824,
      "fundamentals": {
        "trailing_pe": 25.89,
        "forward_pe": 16.99,
        "pb_ratio": 10.41,
        "ps_ratio": 2.26,
        "ev_ebitda": 14.03,
        "earnings_yield": 3.86,
        "revenue_growth": 5.6,
        "earnings_growth": 67.5,
        "growth_tier": "hypergrowth"
      },
      "technicals": {
        "sma_50": 158.34,
        "sma_200": 145.27,
        "rsi": 39.67,
        "week_52_high": 171.48,
        "week_52_low": 127.6,
        "bollinger_position": 48.92,
        "price_vs_sma50": -1.88,
        "price_vs_sma200": 6.95
      },
      "scores": {
        "per_score": 54.0,
        "pbr_score": 10,
        "psr_score": 60,
        "ev_ebitda_score": 40,
        "earnings_yield_score": 20,
        "fundamental_score": 38.2,
        "technical_score": 57.25,
        "value_score": 43.92
      },
      "grade": "C",
      "recommendation": "Weak Hold",
      "fetched_at": "2026-04-02T14:53:03.270676"
    },
    {
      "symbol": "MS",
      "name": "Morgan Stanley",
      "sector": "Financial Services",
      "industry": "Capital Markets",
      "price": 165.43,
      "market_cap": 262687653888,
      "fundamentals": {
        "trailing_pe": 16.22,
        "forward_pe": 13.38,
        "pb_ratio": 2.57,
        "ps_ratio": 3.74,
        "ev_ebitda": 0,
        "earnings_yield": 6.17,
        "revenue_growth": 11.0,
        "earnings_growth": 20.7,
        "growth_tier": "high_growth"
      },
      "technicals": {
        "sma_50": 169.57,
        "sma_200": 159.96,
        "rsi": 69.01,
        "week_52_high": 192.68,
        "week_52_low": 94.33,
        "bollinger_position": 81.83,
        "price_vs_sma50": -2.44,
        "price_vs_sma200": 3.42
      },
      "scores": {
        "per_score": 72.0,
        "pbr_score": 40,
        "psr_score": 40,
        "ev_ebitda_score": 0,
        "earnings_yield_score": 60,
        "fundamental_score": 44.6,
        "technical_score": 41.5,
        "value_score": 43.67
      },
      "grade": "C",
      "recommendation": "Weak Hold",
      "fetched_at": "2026-04-02T14:52:56.270095"
    },
    {
      "symbol": "GS",
      "name": "Goldman Sachs Group, Inc. (The)",
      "sector": "Financial Services",
      "industry": "Capital Markets",
      "price": 859.81,
      "market_cap": 255151128576,
      "fundamentals": {
        "trailing_pe": 16.74,
        "forward_pe": 13.19,
        "pb_ratio": 2.41,
        "ps_ratio": 4.3,
        "ev_ebitda": 0,
        "earnings_yield": 5.97,
        "revenue_growth": 15.2,
        "earnings_growth": 17.3,
        "growth_tier": "high_growth"
      },
      "technicals": {
        "sma_50": 874.51,
        "sma_200": 801.94,
        "rsi": 74.34,
        "week_52_high": 984.7,
        "week_52_low": 439.38,
        "bollinger_position": 95.38,
        "price_vs_sma50": -1.68,
        "price_vs_sma200": 7.22
      },
      "scores": {
        "per_score": 72.0,
        "pbr_score": 40,
        "psr_score": 40,
        "ev_ebitda_score": 0,
        "earnings_yield_score": 60,
        "fundamental_score": 44.6,
        "technical_score": 37.26,
        "value_score": 42.4
      },
      "grade": "C",
      "recommendation": "Weak Hold",
      "fetched_at": "2026-04-02T14:52:55.941331"
    },
    {
      "symbol": "LMT",
      "name": "Lockheed Martin Corporation",
      "sector": "Industrials",
      "industry": "Aerospace & Defense",
      "price": 624.33,
      "market_cap": 143884419072,
      "fundamentals": {
        "trailing_pe": 29.05,
        "forward_pe": 19.49,
        "pb_ratio": 21.27,
        "ps_ratio": 1.92,
        "ev_ebitda": 19.4,
        "earnings_yield": 3.44,
        "revenue_growth": 9.1,
        "earnings_growth": 161.0,
        "growth_tier": "hypergrowth"
      },
      "technicals": {
        "sma_50": 632.78,
        "sma_200": 508.24,
        "rsi": 40.93,
        "week_52_high": 692.0,
        "week_52_low": 410.11,
        "bollinger_position": 38.59,
        "price_vs_sma50": -1.34,
        "price_vs_sma200": 22.84
      },
      "scores": {
        "per_score": 54.0,
        "pbr_score": 0,
        "psr_score": 80,
        "ev_ebitda_score": 20,
        "earnings_yield_score": 20,
        "fundamental_score": 35.2,
        "technical_score": 58.63,
        "value_score": 42.23
      },
      "grade": "C",
      "recommendation": "Weak Hold",
      "fetched_at": "2026-04-02T14:53:09.332330"
    },
    {
      "symbol": "MRK",
      "name": "Merck & Company, Inc.",
      "sector": "Healthcare",
      "industry": "Drug Manufacturers - General",
      "price": 120.8,
      "market_cap": 298664951808,
      "fundamentals": {
        "trailing_pe": 16.62,
        "forward_pe": 12.37,
        "pb_ratio": 5.68,
        "ps_ratio": 4.59,
        "ev_ebitda": 11.5,
        "earnings_yield": 6.02,
        "revenue_growth": 5.0,
        "earnings_growth": -19.3,
        "growth_tier": "declining"
      },
      "technicals": {
        "sma_50": 116.63,
        "sma_200": 95.04,
        "rsi": 72.47,
        "week_52_high": 125.14,
        "week_52_low": 73.31,
        "bollinger_position": 93.9,
        "price_vs_sma50": 3.58,
        "price_vs_sma200": 27.1
      },
      "scores": {
        "per_score": 66.0,
        "pbr_score": 10,
        "psr_score": 40,
        "ev_ebitda_score": 40,
        "earnings_yield_score": 60,
        "fundamental_score": 44.8,
        "technical_score": 35.68,
        "value_score": 42.06
      },
      "grade": "C",
      "recommendation": "Weak Hold",
      "fetched_at": "2026-04-02T14:53:00.029718"
    },
    {
      "symbol": "JPM",
      "name": "JP Morgan Chase & Co.",
      "sector": "Financial Services",
      "industry": "Banks - Diversified",
      "price": 293.65,
      "market_cap": 791983554560,
      "fundamentals": {
        "trailing_pe": 14.66,
        "forward_pe": 12.59,
        "pb_ratio": 2.31,
        "ps_ratio": 4.71,
        "ev_ebitda": 0,
        "earnings_yield": 6.82,
        "revenue_growth": 2.5,
        "earnings_growth": -3.6,
        "growth_tier": "declining"
      },
      "technicals": {
        "sma_50": 299.03,
        "sma_200": 300.83,
        "rsi": 62.26,
        "week_52_high": 337.25,
        "week_52_low": 202.16,
        "bollinger_position": 80.79,
        "price_vs_sma50": -1.8,
        "price_vs_sma200": -2.39
      },
      "scores": {
        "per_score": 80.0,
        "pbr_score": 40,
        "psr_score": 40,
        "ev_ebitda_score": 0,
        "earnings_yield_score": 60,
        "fundamental_score": 47.0,
        "technical_score": 29.85,
        "value_score": 41.86
      },
      "grade": "C",
      "recommendation": "Weak Hold",
      "fetched_at": "2026-04-02T14:52:54.653582"
    },
    {
      "symbol": "HD",
      "name": "Home Depot, Inc. (The)",
      "sector": "Consumer Cyclical",
      "industry": "Home Improvement Retail",
      "price": 323.1,
      "market_cap": 321811316736,
      "fundamentals": {
        "trailing_pe": 22.69,
        "forward_pe": 19.81,
        "pb_ratio": 25.12,
        "ps_ratio": 1.95,
        "ev_ebitda": 15.7,
        "earnings_yield": 4.41,
        "revenue_growth": -3.8,
        "earnings_growth": -14.2,
        "growth_tier": "declining"
      },
      "technicals": {
        "sma_50": 360.49,
        "sma_200": 369.24,
        "rsi": 37.23,
        "week_52_high": 426.75,
        "week_52_low": 318.66,
        "bollinger_position": 21.83,
        "price_vs_sma50": -10.37,
        "price_vs_sma200": -12.5
      },
      "scores": {
        "per_score": 46.0,
        "pbr_score": 0,
        "psr_score": 80,
        "ev_ebitda_score": 20,
        "earnings_yield_score": 20,
        "fundamental_score": 32.8,
        "technical_score": 61.91,
        "value_score": 41.53
      },
      "grade": "C",
      "recommendation": "Weak Hold",
      "fetched_at": "2026-04-02T14:53:04.306121"
    },
    {
      "symbol": "KMI",
      "name": "Kinder Morgan, Inc.",
      "sector": "Energy",
      "industry": "Oil & Gas Midstream",
      "price": 33.08,
      "market_cap": 73585475584,
      "fundamentals": {
        "trailing_pe": 24.14,
        "forward_pe": 22.67,
        "pb_ratio": 2.36,
        "ps_ratio": 4.34,
        "ev_ebitda": 15.0,
        "earnings_yield": 4.14,
        "revenue_growth": 13.1,
        "earnings_growth": 49.3,
        "growth_tier": "hypergrowth"
      },
      "technicals": {
        "sma_50": 32.25,
        "sma_200": 28.15,
        "rsi": 46.74,
        "week_52_high": 34.73,
        "week_52_low": 23.94,
        "bollinger_position": 30.07,
        "price_vs_sma50": 2.55,
        "price_vs_sma200": 17.51
      },
      "scores": {
        "per_score": 40.0,
        "pbr_score": 40,
        "psr_score": 40,
        "ev_ebitda_score": 40,
        "earnings_yield_score": 20,
        "fundamental_score": 37.0,
        "technical_score": 51.15,
        "value_score": 41.24
      },
      "grade": "C",
      "recommendation": "Weak Hold",
      "fetched_at": "2026-04-02T14:53:13.913041"
    },
    {
      "symbol": "CVX",
      "name": "Chevron Corporation",
      "sector": "Energy",
      "industry": "Oil & Gas Integrated",
      "price": 200.34,
      "market_cap": 400540532736,
      "fundamentals": {
        "trailing_pe": 30.22,
        "forward_pe": 19.92,
        "pb_ratio": 2.13,
        "ps_ratio": 2.17,
        "ev_ebitda": 11.7,
        "earnings_yield": 3.31,
        "revenue_growth": -8.2,
        "earnings_growth": -23.8,
        "growth_tier": "declining"
      },
      "technicals": {
        "sma_50": 187.62,
        "sma_200": 159.95,
        "rsi": 55.13,
        "week_52_high": 214.71,
        "week_52_low": 132.04,
        "bollinger_position": 51.34,
        "price_vs_sma50": 6.77,
        "price_vs_sma200": 25.25
      },
      "scores": {
        "per_score": 32.0,
        "pbr_score": 40,
        "psr_score": 60,
        "ev_ebitda_score": 40,
        "earnings_yield_score": 20,
        "fundamental_score": 37.6,
        "technical_score": 49.33,
        "value_score": 41.12
      },
      "grade": "C",
      "recommendation": "Weak Hold",
      "fetched_at": "2026-04-02T14:53:11.057373"
    },
    {
      "symbol": "OXY",
      "name": "Occidental Petroleum Corporatio",
      "sector": "Energy",
      "industry": "Oil & Gas E&P",
      "price": 63.2,
      "market_cap": 62679797760,
      "fundamentals": {
        "trailing_pe": 46.82,
        "forward_pe": 20.54,
        "pb_ratio": 2.25,
        "ps_ratio": 2.9,
        "ev_ebitda": 8.14,
        "earnings_yield": 2.14,
        "revenue_growth": 148.9,
        "earnings_growth": 0,
        "growth_tier": "hypergrowth"
      },
      "technicals": {
        "sma_50": 52.63,
        "sma_200": 45.34,
        "rsi": 67.28,
        "week_52_high": 67.45,
        "week_52_low": 34.78,
        "bollinger_position": 72.17,
        "price_vs_sma50": 20.09,
        "price_vs_sma200": 39.41
      },
      "scores": {
        "per_score": 34.0,
        "pbr_score": 40,
        "psr_score": 60,
        "ev_ebitda_score": 60,
        "earnings_yield_score": 0,
        "fundamental_score": 39.2,
        "technical_score": 44.02,
        "value_score": 40.65
      },
      "grade": "C",
      "recommendation": "Weak Hold",
      "fetched_at": "2026-04-02T14:53:13.593869"
    },
    {
      "symbol": "UNP",
      "name": "Union Pacific Corporation",
      "sector": "Industrials",
      "industry": "Railroads",
      "price": 242.57,
      "market_cap": 144005578752,
      "fundamentals": {
        "trailing_pe": 20.23,
        "forward_pe": 17.89,
        "pb_ratio": 7.79,
        "ps_ratio": 5.88,
        "ev_ebitda": 14.12,
        "earnings_yield": 4.94,
        "revenue_growth": -0.6,
        "earnings_growth": 6.8,
        "growth_tier": "stable"
      },
      "technicals": {
        "sma_50": 248.24,
        "sma_200": 230.28,
        "rsi": 50.27,
        "week_52_high": 268.14,
        "week_52_low": 204.66,
        "bollinger_position": 50.14,
        "price_vs_sma50": -2.29,
        "price_vs_sma200": 5.34
      },
      "scores": {
        "per_score": 48.0,
        "pbr_score": 10,
        "psr_score": 20,
        "ev_ebitda_score": 40,
        "earnings_yield_score": 40,
        "fundamental_score": 33.4,
        "technical_score": 56.95,
        "value_score": 40.47
      },
      "grade": "C",
      "recommendation": "Weak Hold",
      "fetched_at": "2026-04-02T14:53:10.089000"
    },
    {
      "symbol": "ABT",
      "name": "Abbott Laboratories",
      "sector": "Healthcare",
      "industry": "Medical Devices",
      "price": 103.3,
      "market_cap": 179491356672,
      "fundamentals": {
        "trailing_pe": 27.77,
        "forward_pe": 16.92,
        "pb_ratio": 3.44,
        "ps_ratio": 4.05,
        "ev_ebitda": 15.27,
        "earnings_yield": 3.6,
        "revenue_growth": 4.4,
        "earnings_growth": -80.9,
        "growth_tier": "declining"
      },
      "technicals": {
        "sma_50": 109.49,
        "sma_200": 123.52,
        "rsi": 34.29,
        "week_52_high": 139.06,
        "week_52_low": 100.88,
        "bollinger_position": 23.44,
        "price_vs_sma50": -5.66,
        "price_vs_sma200": -16.37
      },
      "scores": {
        "per_score": 46.0,
        "pbr_score": 20,
        "psr_score": 40,
        "ev_ebitda_score": 20,
        "earnings_yield_score": 20,
        "fundamental_score": 30.8,
        "technical_score": 59.66,
        "value_score": 39.46
      },
      "grade": "D",
      "recommendation": "Avoid",
      "fetched_at": "2026-04-02T14:53:00.703296"
    },
    {
      "symbol": "MCD",
      "name": "McDonald's Corporation",
      "sector": "Consumer Cyclical",
      "industry": "Restaurants",
      "price": 304.91,
      "market_cap": 217585123328,
      "fundamentals": {
        "trailing_pe": 25.52,
        "forward_pe": 21.22,
        "pb_ratio": -121.04,
        "ps_ratio": 8.09,
        "ev_ebitda": 18.66,
        "earnings_yield": 3.92,
        "revenue_growth": 9.7,
        "earnings_growth": 8.2,
        "growth_tier": "moderate_growth"
      },
      "technicals": {
        "sma_50": 320.44,
        "sma_200": 305.68,
        "rsi": 22.67,
        "week_52_high": 341.75,
        "week_52_low": 283.47,
        "bollinger_position": 18.95,
        "price_vs_sma50": -4.85,
        "price_vs_sma200": -0.25
      },
      "scores": {
        "per_score": 40.0,
        "pbr_score": 0,
        "psr_score": 20,
        "ev_ebitda_score": 20,
        "earnings_yield_score": 20,
        "fundamental_score": 22.0,
        "technical_score": 78.71,
        "value_score": 39.01
      },
      "grade": "D",
      "recommendation": "Avoid",
      "fetched_at": "2026-04-02T14:53:04.827344"
    },
    {
      "symbol": "META",
      "name": "Meta Platforms, Inc.",
      "sector": "Communication Services",
      "industry": "Internet Content & Information",
      "price": 571.07,
      "market_cap": 1444540579840,
      "fundamentals": {
        "trailing_pe": 24.28,
        "forward_pe": 15.88,
        "pb_ratio": 6.65,
        "ps_ratio": 7.19,
        "ev_ebitda": 14.41,
        "earnings_yield": 4.12,
        "revenue_growth": 23.8,
        "earnings_growth": 10.7,
        "growth_tier": "high_growth"
      },
      "technicals": {
        "sma_50": 639.17,
        "sma_200": 683.96,
        "rsi": 39.6,
        "week_52_high": 796.25,
        "week_52_low": 479.8,
        "bollinger_position": 29.16,
        "price_vs_sma50": -10.65,
        "price_vs_sma200": -16.51
      },
      "scores": {
        "per_score": 52.0,
        "pbr_score": 10,
        "psr_score": 20,
        "ev_ebitda_score": 40,
        "earnings_yield_score": 20,
        "fundamental_score": 31.6,
        "technical_score": 55.86,
        "value_score": 38.88
      },
      "grade": "D",
      "recommendation": "Avoid",
      "fetched_at": "2026-04-02T14:52:53.050874"
    },
    {
      "symbol": "MSFT",
      "name": "Microsoft Corporation",
      "sector": "Technology",
      "industry": "Software - Infrastructure",
      "price": 368.85,
      "market_cap": 2741424357376,
      "fundamentals": {
        "trailing_pe": 23.07,
        "forward_pe": 19.57,
        "pb_ratio": 7.01,
        "ps_ratio": 8.97,
        "ev_ebitda": 15.84,
        "earnings_yield": 4.34,
        "revenue_growth": 16.7,
        "earnings_growth": 59.8,
        "growth_tier": "hypergrowth"
      },
      "technicals": {
        "sma_50": 403.15,
        "sma_200": 475.24,
        "rsi": 29.32,
        "week_52_high": 555.45,
        "week_52_low": 344.79,
        "bollinger_position": 25.91,
        "price_vs_sma50": -8.51,
        "price_vs_sma200": -22.39
      },
      "scores": {
        "per_score": 54.0,
        "pbr_score": 10,
        "psr_score": 20,
        "ev_ebitda_score": 20,
        "earnings_yield_score": 20,
        "fundamental_score": 28.2,
        "technical_score": 63.71,
        "value_score": 38.85
      },
      "grade": "D",
      "recommendation": "Avoid",
      "fetched_at": "2026-04-02T14:52:52.410128"
    },
    {
      "symbol": "MMM",
      "name": "3M Company",
      "sector": "Industrials",
      "industry": "Conglomerates",
      "price": 144.78,
      "market_cap": 76255625216,
      "fundamentals": {
        "trailing_pe": 24.13,
        "forward_pe": 15.43,
        "pb_ratio": 16.33,
        "ps_ratio": 3.06,
        "ev_ebitda": 13.59,
        "earnings_yield": 4.14,
        "revenue_growth": 2.0,
        "earnings_growth": -19.9,
        "growth_tier": "declining"
      },
      "technicals": {
        "sma_50": 156.97,
        "sma_200": 157.23,
        "rsi": 37.81,
        "week_52_high": 177.41,
        "week_52_low": 121.98,
        "bollinger_position": 33.6,
        "price_vs_sma50": -7.77,
        "price_vs_sma200": -7.92
      },
      "scores": {
        "per_score": 46.0,
        "pbr_score": 10,
        "psr_score": 40,
        "ev_ebitda_score": 40,
        "earnings_yield_score": 20,
        "fundamental_score": 32.8,
        "technical_score": 52.46,
        "value_score": 38.7
      },
      "grade": "D",
      "recommendation": "Avoid",
      "fetched_at": "2026-04-02T14:53:07.713112"
    },
    {
      "symbol": "AXP",
      "name": "American Express Company",
      "sector": "Financial Services",
      "industry": "Credit Services",
      "price": 299.02,
      "market_cap": 205311311872,
      "fundamentals": {
        "trailing_pe": 19.45,
        "forward_pe": 14.84,
        "pb_ratio": 6.13,
        "ps_ratio": 3.07,
        "ev_ebitda": 0,
        "earnings_yield": 5.14,
        "revenue_growth": 10.6,
        "earnings_growth": 16.6,
        "growth_tier": "moderate_growth"
      },
      "technicals": {
        "sma_50": 325.41,
        "sma_200": 334.45,
        "rsi": 48.85,
        "week_52_high": 387.49,
        "week_52_low": 220.43,
        "bollinger_position": 44.08,
        "price_vs_sma50": -8.11,
        "price_vs_sma200": -10.59
      },
      "scores": {
        "per_score": 70.0,
        "pbr_score": 10,
        "psr_score": 40,
        "ev_ebitda_score": 0,
        "earnings_yield_score": 40,
        "fundamental_score": 35.0,
        "technical_score": 44.32,
        "value_score": 37.8
      },
      "grade": "D",
      "recommendation": "Avoid",
      "fetched_at": "2026-04-02T14:52:57.287046"
    },
    {
      "symbol": "RTX",
      "name": "RTX Corporation",
      "sector": "Industrials",
      "industry": "Aerospace & Defense",
      "price": 196.0,
      "market_cap": 263810957312,
      "fundamentals": {
        "trailing_pe": 39.44,
        "forward_pe": 26.06,
        "pb_ratio": 4.03,
        "ps_ratio": 2.98,
        "ev_ebitda": 20.07,
        "earnings_yield": 2.54,
        "revenue_growth": 12.1,
        "earnings_growth": 8.3,
        "growth_tier": "moderate_growth"
      },
      "technicals": {
        "sma_50": 199.92,
        "sma_200": 173.42,
        "rsi": 37.38,
        "week_52_high": 214.5,
        "week_52_low": 112.27,
        "bollinger_position": 36.74,
        "price_vs_sma50": -1.96,
        "price_vs_sma200": 13.02
      },
      "scores": {
        "per_score": 30.0,
        "pbr_score": 20,
        "psr_score": 60,
        "ev_ebitda_score": 10,
        "earnings_yield_score": 20,
        "fundamental_score": 27.0,
        "technical_score": 56.32,
        "value_score": 35.8
      },
      "grade": "D",
      "recommendation": "Avoid",
      "fetched_at": "2026-04-02T14:53:08.934932"
    },
    {
      "symbol": "BLK",
      "name": "BlackRock, Inc.",
      "sector": "Financial Services",
      "industry": "Asset Management",
      "price": 959.44,
      "market_cap": 149232779264,
      "fundamentals": {
        "trailing_pe": 27.16,
        "forward_pe": 15.55,
        "pb_ratio": 2.66,
        "ps_ratio": 6.16,
        "ev_ebitda": 16.03,
        "earnings_yield": 3.68,
        "revenue_growth": 23.4,
        "earnings_growth": -31.7,
        "growth_tier": "declining"
      },
      "technicals": {
        "sma_50": 1030.41,
        "sma_200": 1073.32,
        "rsi": 60.53,
        "week_52_high": 1219.94,
        "week_52_low": 773.74,
        "bollinger_position": 53.99,
        "price_vs_sma50": -6.89,
        "price_vs_sma200": -10.61
      },
      "scores": {
        "per_score": 46.0,
        "pbr_score": 40,
        "psr_score": 20,
        "ev_ebitda_score": 20,
        "earnings_yield_score": 20,
        "fundamental_score": 31.8,
        "technical_score": 41.5,
        "value_score": 34.71
      },
      "grade": "D",
      "recommendation": "Avoid",
      "fetched_at": "2026-04-02T14:52:57.583917"
    },
    {
      "symbol": "TMO",
      "name": "Thermo Fisher Scientific Inc",
      "sector": "Healthcare",
      "industry": "Diagnostics & Research",
      "price": 500.47,
      "market_cap": 185916719104,
      "fundamentals": {
        "trailing_pe": 28.2,
        "forward_pe": 18.6,
        "pb_ratio": 3.53,
        "ps_ratio": 4.17,
        "ev_ebitda": 19.31,
        "earnings_yield": 3.55,
        "revenue_growth": 7.2,
        "earnings_growth": 9.3,
        "growth_tier": "moderate_growth"
      },
      "technicals": {
        "sma_50": 521.42,
        "sma_200": 517.68,
        "rsi": 70.76,
        "week_52_high": 643.99,
        "week_52_low": 385.46,
        "bollinger_position": 80.73,
        "price_vs_sma50": -4.02,
        "price_vs_sma200": -3.32
      },
      "scores": {
        "per_score": 50.0,
        "pbr_score": 20,
        "psr_score": 40,
        "ev_ebitda_score": 20,
        "earnings_yield_score": 20,
        "fundamental_score": 32.0,
        "technical_score": 40.18,
        "value_score": 34.45
      },
      "grade": "D",
      "recommendation": "Avoid",
      "fetched_at": "2026-04-02T14:53:00.323343"
    },
    {
      "symbol": "DHR",
      "name": "Danaher Corporation",
      "sector": "Healthcare",
      "industry": "Diagnostics & Research",
      "price": 191.51,
      "market_cap": 135527972864,
      "fundamentals": {
        "trailing_pe": 38.0,
        "forward_pe": 21.04,
        "pb_ratio": 2.58,
        "ps_ratio": 5.52,
        "ev_ebitda": 19.14,
        "earnings_yield": 2.63,
        "revenue_growth": 4.6,
        "earnings_growth": 12.5,
        "growth_tier": "moderate_growth"
      },
      "technicals": {
        "sma_50": 205.54,
        "sma_200": 209.02,
        "rsi": 56.66,
        "week_52_high": 242.8,
        "week_52_low": 171.0,
        "bollinger_position": 58.69,
        "price_vs_sma50": -6.83,
        "price_vs_sma200": -8.38
      },
      "scores": {
        "per_score": 30.0,
        "pbr_score": 40,
        "psr_score": 20,
        "ev_ebitda_score": 20,
        "earnings_yield_score": 20,
        "fundamental_score": 27.0,
        "technical_score": 49.58,
        "value_score": 33.77
      },
      "grade": "D",
      "recommendation": "Avoid",
      "fetched_at": "2026-04-02T14:53:01.006472"
    },
    {
      "symbol": "INTC",
      "name": "Intel Corporation",
      "sector": "Technology",
      "industry": "Semiconductors",
      "price": 49.61,
      "market_cap": 249067225088,
      "fundamentals": {
        "trailing_pe": 0,
        "forward_pe": 50.0,
        "pb_ratio": 2.17,
        "ps_ratio": 4.71,
        "ev_ebitda": 20.71,
        "earnings_yield": 0,
        "revenue_growth": -4.1,
        "earnings_growth": 0,
        "growth_tier": "declining"
      },
      "technicals": {
        "sma_50": 46.15,
        "sma_200": 35.29,
        "rsi": 58.05,
        "week_52_high": 54.6,
        "week_52_low": 17.67,
        "bollinger_position": 100,
        "price_vs_sma50": 7.5,
        "price_vs_sma200": 40.58
      },
      "scores": {
        "per_score": 41.0,
        "pbr_score": 40,
        "psr_score": 40,
        "ev_ebitda_score": 10,
        "earnings_yield_score": 0,
        "fundamental_score": 28.3,
        "technical_score": 45.0,
        "value_score": 33.31
      },
      "grade": "D",
      "recommendation": "Avoid",
      "fetched_at": "2026-04-02T14:52:53.934453"
    },
    {
      "symbol": "HON",
      "name": "Honeywell International Inc.",
      "sector": "Industrials",
      "industry": "Conglomerates",
      "price": 228.82,
      "market_cap": 145455316992,
      "fundamentals": {
        "trailing_pe": 32.97,
        "forward_pe": 19.94,
        "pb_ratio": 10.46,
        "ps_ratio": 3.88,
        "ev_ebitda": 19.94,
        "earnings_yield": 3.03,
        "revenue_growth": -3.3,
        "earnings_growth": -76.4,
        "growth_tier": "declining"
      },
      "technicals": {
        "sma_50": 233.04,
        "sma_200": 209.2,
        "rsi": 40.06,
        "week_52_high": 248.18,
        "week_52_low": 169.05,
        "bollinger_position": 46.58,
        "price_vs_sma50": -1.81,
        "price_vs_sma200": 9.38
      },
      "scores": {
        "per_score": 32.0,
        "pbr_score": 10,
        "psr_score": 40,
        "ev_ebitda_score": 20,
        "earnings_yield_score": 20,
        "fundamental_score": 24.6,
        "technical_score": 52.85,
        "value_score": 33.08
      },
      "grade": "D",
      "recommendation": "Avoid",
      "fetched_at": "2026-04-02T14:53:08.112928"
    },
    {
      "symbol": "V",
      "name": "Visa Inc.",
      "sector": "Financial Services",
      "industry": "Credit Services",
      "price": 299.68,
      "market_cap": 577794867200,
      "fundamentals": {
        "trailing_pe": 28.11,
        "forward_pe": 20.61,
        "pb_ratio": 14.96,
        "ps_ratio": 13.96,
        "ev_ebitda": 19.82,
        "earnings_yield": 3.56,
        "revenue_growth": 14.6,
        "earnings_growth": 17.4,
        "growth_tier": "high_growth"
      },
      "technicals": {
        "sma_50": 315.62,
        "sma_200": 335.44,
        "rsi": 41.44,
        "week_52_high": 375.51,
        "week_52_low": 293.89,
        "bollinger_position": 26.75,
        "price_vs_sma50": -5.05,
        "price_vs_sma200": -10.66
      },
      "scores": {
        "per_score": 40.0,
        "pbr_score": 10,
        "psr_score": 10,
        "ev_ebitda_score": 20,
        "earnings_yield_score": 20,
        "fundamental_score": 22.5,
        "technical_score": 56.02,
        "value_score": 32.56
      },
      "grade": "D",
      "recommendation": "Avoid",
      "fetched_at": "2026-04-02T14:52:56.528718"
    },
    {
      "symbol": "AMZN",
      "name": "Amazon.com, Inc.",
      "sector": "Consumer Cyclical",
      "industry": "Internet Retail",
      "price": 210.28,
      "market_cap": 2257339023360,
      "fundamentals": {
        "trailing_pe": 29.29,
        "forward_pe": 22.39,
        "pb_ratio": 5.49,
        "ps_ratio": 3.15,
        "ev_ebitda": 15.89,
        "earnings_yield": 3.41,
        "revenue_growth": 13.6,
        "earnings_growth": 5.0,
        "growth_tier": "moderate_growth"
      },
      "technicals": {
        "sma_50": 215.01,
        "sma_200": 224.55,
        "rsi": 52.44,
        "week_52_high": 258.6,
        "week_52_low": 161.38,
        "bollinger_position": 55.59,
        "price_vs_sma50": -2.2,
        "price_vs_sma200": -6.36
      },
      "scores": {
        "per_score": 40.0,
        "pbr_score": 10,
        "psr_score": 40,
        "ev_ebitda_score": 20,
        "earnings_yield_score": 20,
        "fundamental_score": 27.0,
        "technical_score": 43.94,
        "value_score": 32.08
      },
      "grade": "D",
      "recommendation": "Avoid",
      "fetched_at": "2026-04-02T14:52:52.872154"
    },
    {
      "symbol": "JNJ",
      "name": "Johnson & Johnson",
      "sector": "Healthcare",
      "industry": "Drug Manufacturers - General",
      "price": 246.49,
      "market_cap": 594016010240,
      "fundamentals": {
        "trailing_pe": 22.35,
        "forward_pe": 19.6,
        "pb_ratio": 7.28,
        "ps_ratio": 6.31,
        "ev_ebitda": 18.25,
        "earnings_yield": 4.47,
        "revenue_growth": 9.1,
        "earnings_growth": 48.6,
        "growth_tier": "hypergrowth"
      },
      "technicals": {
        "sma_50": 238.42,
        "sma_200": 196.65,
        "rsi": 60.54,
        "week_52_high": 251.71,
        "week_52_low": 141.5,
        "bollinger_position": 95.68,
        "price_vs_sma50": 3.38,
        "price_vs_sma200": 25.34
      },
      "scores": {
        "per_score": 54.0,
        "pbr_score": 10,
        "psr_score": 20,
        "ev_ebitda_score": 20,
        "earnings_yield_score": 20,
        "fundamental_score": 28.2,
        "technical_score": 40.31,
        "value_score": 31.83
      },
      "grade": "D",
      "recommendation": "Avoid",
      "fetched_at": "2026-04-02T14:52:58.581177"
    },
    {
      "symbol": "GOOGL",
      "name": "Alphabet Inc.",
      "sector": "Communication Services",
      "industry": "Internet Content & Information",
      "price": 295.92,
      "market_cap": 3579744616448,
      "fundamentals": {
        "trailing_pe": 27.4,
        "forward_pe": 22.03,
        "pb_ratio": 8.61,
        "ps_ratio": 8.89,
        "ev_ebitda": 23.56,
        "earnings_yield": 3.65,
        "revenue_growth": 18.0,
        "earnings_growth": 31.1,
        "growth_tier": "high_growth"
      },
      "technicals": {
        "sma_50": 310.29,
        "sma_200": 264.69,
        "rsi": 45.73,
        "week_52_high": 349.0,
        "week_52_low": 140.53,
        "bollinger_position": 46.22,
        "price_vs_sma50": -4.63,
        "price_vs_sma200": 11.8
      },
      "scores": {
        "per_score": 40.0,
        "pbr_score": 10,
        "psr_score": 20,
        "ev_ebitda_score": 10,
        "earnings_yield_score": 20,
        "fundamental_score": 22.0,
        "technical_score": 54.31,
        "value_score": 31.69
      },
      "grade": "D",
      "recommendation": "Avoid",
      "fetched_at": "2026-04-02T14:52:52.683349"
    },
    {
      "symbol": "DE",
      "name": "Deere & Company",
      "sector": "Industrials",
      "industry": "Farm & Heavy Construction Machinery",
      "price": 575.35,
      "market_cap": 155406221312,
      "fundamentals": {
        "trailing_pe": 32.41,
        "forward_pe": 24.79,
        "pb_ratio": 5.91,
        "ps_ratio": 3.33,
        "ev_ebitda": 24.7,
        "earnings_yield": 3.09,
        "revenue_growth": 13.0,
        "earnings_growth": -24.1,
        "growth_tier": "declining"
      },
      "technicals": {
        "sma_50": 580.53,
        "sma_200": 505.64,
        "rsi": 49.77,
        "week_52_high": 674.19,
        "week_52_low": 404.42,
        "bollinger_position": 50.94,
        "price_vs_sma50": -0.89,
        "price_vs_sma200": 13.79
      },
      "scores": {
        "per_score": 26.0,
        "pbr_score": 10,
        "psr_score": 40,
        "ev_ebitda_score": 10,
        "earnings_yield_score": 20,
        "fundamental_score": 20.8,
        "technical_score": 53.7,
        "value_score": 30.67
      },
      "grade": "D",
      "recommendation": "Avoid",
      "fetched_at": "2026-04-02T14:53:09.742240"
    },
    {
      "symbol": "KO",
      "name": "Coca-Cola Company (The)",
      "sector": "Consumer Defensive",
      "industry": "Beverages - Non-Alcoholic",
      "price": 76.85,
      "market_cap": 330752655360,
      "fundamentals": {
        "trailing_pe": 25.28,
        "forward_pe": 22.22,
        "pb_ratio": 10.28,
        "ps_ratio": 6.9,
        "ev_ebitda": 22.48,
        "earnings_yield": 3.96,
        "revenue_growth": 2.4,
        "earnings_growth": 3.6,
        "growth_tier": "stable"
      },
      "technicals": {
        "sma_50": 76.71,
        "sma_200": 70.41,
        "rsi": 46.94,
        "week_52_high": 82.0,
        "week_52_low": 65.35,
        "bollinger_position": 64.91,
        "price_vs_sma50": 0.17,
        "price_vs_sma200": 9.14
      },
      "scores": {
        "per_score": 40.0,
        "pbr_score": 10,
        "psr_score": 20,
        "ev_ebitda_score": 10,
        "earnings_yield_score": 20,
        "fundamental_score": 22.0,
        "technical_score": 49.74,
        "value_score": 30.32
      },
      "grade": "D",
      "recommendation": "Avoid",
      "fetched_at": "2026-04-02T14:53:02.866274"
    },
    {
      "symbol": "NVDA",
      "name": "NVIDIA Corporation",
      "sector": "Technology",
      "industry": "Semiconductors",
      "price": 175.87,
      "market_cap": 4274520326144,
      "fundamentals": {
        "trailing_pe": 35.89,
        "forward_pe": 15.82,
        "pb_ratio": 27.17,
        "ps_ratio": 19.79,
        "ev_ebitda": 31.67,
        "earnings_yield": 2.79,
        "revenue_growth": 73.2,
        "earnings_growth": 95.6,
        "growth_tier": "hypergrowth"
      },
      "technicals": {
        "sma_50": 182.61,
        "sma_200": 179.79,
        "rsi": 45.09,
        "week_52_high": 212.19,
        "week_52_low": 86.62,
        "bollinger_position": 42.3,
        "price_vs_sma50": -3.69,
        "price_vs_sma200": -2.18
      },
      "scores": {
        "per_score": 48.0,
        "pbr_score": 0,
        "psr_score": 10,
        "ev_ebitda_score": 10,
        "earnings_yield_score": 20,
        "fundamental_score": 20.9,
        "technical_score": 50.39,
        "value_score": 29.75
      },
      "grade": "D",
      "recommendation": "Avoid",
      "fetched_at": "2026-04-02T14:52:53.247722"
    },
    {
      "symbol": "WMT",
      "name": "Walmart Inc.",
      "sector": "Consumer Defensive",
      "industry": "Discount Stores",
      "price": 124.91,
      "market_cap": 995831971840,
      "fundamentals": {
        "trailing_pe": 45.75,
        "forward_pe": 38.03,
        "pb_ratio": 9.99,
        "ps_ratio": 1.4,
        "ev_ebitda": 24.05,
        "earnings_yield": 2.19,
        "revenue_growth": 5.6,
        "earnings_growth": -19.0,
        "growth_tier": "declining"
      },
      "technicals": {
        "sma_50": 124.26,
        "sma_200": 108.87,
        "rsi": 45.46,
        "week_52_high": 134.69,
        "week_52_low": 79.81,
        "bollinger_position": 71.2,
        "price_vs_sma50": 0.52,
        "price_vs_sma200": 14.73
      },
      "scores": {
        "per_score": 20.0,
        "pbr_score": 10,
        "psr_score": 80,
        "ev_ebitda_score": 10,
        "earnings_yield_score": 0,
        "fundamental_score": 22.0,
        "technical_score": 46.03,
        "value_score": 29.21
      },
      "grade": "D",
      "recommendation": "Avoid",
      "fetched_at": "2026-04-02T14:53:03.696442"
    },
    {
      "symbol": "ABBV",
      "name": "AbbVie Inc.",
      "sector": "Healthcare",
      "industry": "Drug Manufacturers - General",
      "price": 213.09,
      "market_cap": 376905564160,
      "fundamentals": {
        "trailing_pe": 90.29,
        "forward_pe": 13.22,
        "pb_ratio": -115.18,
        "ps_ratio": 6.16,
        "ev_ebitda": 15.15,
        "earnings_yield": 1.11,
        "revenue_growth": 10.0,
        "earnings_growth": 0,
        "growth_tier": "moderate_growth"
      },
      "technicals": {
        "sma_50": 221.69,
        "sma_200": 214.18,
        "rsi": 41.48,
        "week_52_high": 244.81,
        "week_52_low": 164.39,
        "bollinger_position": 42.13,
        "price_vs_sma50": -3.88,
        "price_vs_sma200": -0.51
      },
      "scores": {
        "per_score": 40.0,
        "pbr_score": 0,
        "psr_score": 20,
        "ev_ebitda_score": 20,
        "earnings_yield_score": 0,
        "fundamental_score": 19.0,
        "technical_score": 50.88,
        "value_score": 28.56
      },
      "grade": "D",
      "recommendation": "Avoid",
      "fetched_at": "2026-04-02T14:52:59.628492"
    },
    {
      "symbol": "SBUX",
      "name": "Starbucks Corporation",
      "sector": "Consumer Cyclical",
      "industry": "Restaurants",
      "price": 90.74,
      "market_cap": 103380074496,
      "fundamentals": {
        "trailing_pe": 75.62,
        "forward_pe": 30.73,
        "pb_ratio": -12.32,
        "ps_ratio": 2.74,
        "ev_ebitda": 23.58,
        "earnings_yield": 1.32,
        "revenue_growth": 5.5,
        "earnings_growth": -62.5,
        "growth_tier": "declining"
      },
      "technicals": {
        "sma_50": 95.4,
        "sma_200": 88.61,
        "rsi": 34.3,
        "week_52_high": 104.82,
        "week_52_low": 75.5,
        "bollinger_position": 29.13,
        "price_vs_sma50": -4.88,
        "price_vs_sma200": 2.4
      },
      "scores": {
        "per_score": 6.0,
        "pbr_score": 0,
        "psr_score": 60,
        "ev_ebitda_score": 10,
        "earnings_yield_score": 0,
        "fundamental_score": 12.8,
        "technical_score": 64.41,
        "value_score": 28.28
      },
      "grade": "D",
      "recommendation": "Avoid",
      "fetched_at": "2026-04-02T14:53:05.600785"
    },
    {
      "symbol": "MA",
      "name": "Mastercard Incorporated",
      "sector": "Financial Services",
      "industry": "Credit Services",
      "price": 494.42,
      "market_cap": 441239044096,
      "fundamentals": {
        "trailing_pe": 29.93,
        "forward_pe": 21.82,
        "pb_ratio": 57.13,
        "ps_ratio": 13.46,
        "ev_ebitda": 21.78,
        "earnings_yield": 3.34,
        "revenue_growth": 17.6,
        "earnings_growth": 24.2,
        "growth_tier": "high_growth"
      },
      "technicals": {
        "sma_50": 517.31,
        "sma_200": 552.01,
        "rsi": 48.07,
        "week_52_high": 601.77,
        "week_52_low": 465.59,
        "bollinger_position": 33.66,
        "price_vs_sma50": -4.42,
        "price_vs_sma200": -10.43
      },
      "scores": {
        "per_score": 40.0,
        "pbr_score": 0,
        "psr_score": 10,
        "ev_ebitda_score": 10,
        "earnings_yield_score": 20,
        "fundamental_score": 18.5,
        "technical_score": 50.93,
        "value_score": 28.23
      },
      "grade": "D",
      "recommendation": "Avoid",
      "fetched_at": "2026-04-02T14:52:56.906607"
    },
    {
      "symbol": "AAPL",
      "name": "Apple Inc.",
      "sector": "Technology",
      "industry": "Consumer Electronics",
      "price": 254.36,
      "market_cap": 3738564296704,
      "fundamentals": {
        "trailing_pe": 32.2,
        "forward_pe": 27.31,
        "pb_ratio": 42.41,
        "ps_ratio": 8.58,
        "ev_ebitda": 24.7,
        "earnings_yield": 3.11,
        "revenue_growth": 15.7,
        "earnings_growth": 18.3,
        "growth_tier": "high_growth"
      },
      "technicals": {
        "sma_50": 260.27,
        "sma_200": 248.8,
        "rsi": 56.67,
        "week_52_high": 288.62,
        "week_52_low": 169.21,
        "bollinger_position": 56.35,
        "price_vs_sma50": -2.27,
        "price_vs_sma200": 2.24
      },
      "scores": {
        "per_score": 32.0,
        "pbr_score": 0,
        "psr_score": 20,
        "ev_ebitda_score": 10,
        "earnings_yield_score": 20,
        "fundamental_score": 17.6,
        "technical_score": 51.15,
        "value_score": 27.66
      },
      "grade": "D",
      "recommendation": "Avoid",
      "fetched_at": "2026-04-02T14:52:52.198278"
    },
    {
      "symbol": "GE",
      "name": "GE Aerospace",
      "sector": "Industrials",
      "industry": "Aerospace & Defense",
      "price": 286.42,
      "market_cap": 302116929536,
      "fundamentals": {
        "trailing_pe": 35.58,
        "forward_pe": 33.35,
        "pb_ratio": 16.08,
        "ps_ratio": 6.59,
        "ev_ebitda": 29.59,
        "earnings_yield": 2.81,
        "revenue_growth": 17.6,
        "earnings_growth": 37.4,
        "growth_tier": "hypergrowth"
      },
      "technicals": {
        "sma_50": 311.16,
        "sma_200": 292.94,
        "rsi": 41.92,
        "week_52_high": 348.48,
        "week_52_low": 159.36,
        "bollinger_position": 29.78,
        "price_vs_sma50": -7.95,
        "price_vs_sma200": -2.23
      },
      "scores": {
        "per_score": 20.0,
        "pbr_score": 10,
        "psr_score": 20,
        "ev_ebitda_score": 10,
        "earnings_yield_score": 20,
        "fundamental_score": 16.0,
        "technical_score": 54.05,
        "value_score": 27.42
      },
      "grade": "D",
      "recommendation": "Avoid",
      "fetched_at": "2026-04-02T14:53:07.191158"
    },
    {
      "symbol": "BA",
      "name": "Boeing Company (The)",
      "sector": "Industrials",
      "industry": "Aerospace & Defense",
      "price": 205.76,
      "market_cap": 161691369472,
      "fundamentals": {
        "trailing_pe": 82.63,
        "forward_pe": 43.8,
        "pb_ratio": 29.63,
        "ps_ratio": 1.81,
        "ev_ebitda": -58.84,
        "earnings_yield": 1.21,
        "revenue_growth": 57.1,
        "earnings_growth": 0,
        "growth_tier": "hypergrowth"
      },
      "technicals": {
        "sma_50": 224.14,
        "sma_200": 218.6,
        "rsi": 46.58,
        "week_52_high": 254.35,
        "week_52_low": 128.88,
        "bollinger_position": 50.61,
        "price_vs_sma50": -8.2,
        "price_vs_sma200": -5.88
      },
      "scores": {
        "per_score": 14.0,
        "pbr_score": 0,
        "psr_score": 80,
        "ev_ebitda_score": 0,
        "earnings_yield_score": 0,
        "fundamental_score": 16.2,
        "technical_score": 50.63,
        "value_score": 26.53
      },
      "grade": "D",
      "recommendation": "Avoid",
      "fetched_at": "2026-04-02T14:53:06.804954"
    },
    {
      "symbol": "COST",
      "name": "Costco Wholesale Corporation",
      "sector": "Consumer Defensive",
      "industry": "Discount Stores",
      "price": 1005.76,
      "market_cap": 446424088576,
      "fundamentals": {
        "trailing_pe": 52.3,
        "forward_pe": 44.82,
        "pb_ratio": 13.91,
        "ps_ratio": 1.56,
        "ev_ebitda": 32.11,
        "earnings_yield": 1.91,
        "revenue_growth": 9.2,
        "earnings_growth": 13.9,
        "growth_tier": "moderate_growth"
      },
      "technicals": {
        "sma_50": 987.87,
        "sma_200": 946.51,
        "rsi": 48.39,
        "week_52_high": 1067.08,
        "week_52_low": 844.06,
        "bollinger_position": 80.39,
        "price_vs_sma50": 1.81,
        "price_vs_sma200": 6.26
      },
      "scores": {
        "per_score": 10.0,
        "pbr_score": 10,
        "psr_score": 80,
        "ev_ebitda_score": 10,
        "earnings_yield_score": 0,
        "fundamental_score": 19.0,
        "technical_score": 43.59,
        "value_score": 26.38
      },
      "grade": "D",
      "recommendation": "Avoid",
      "fetched_at": "2026-04-02T14:53:03.989034"
    },
    {
      "symbol": "CAT",
      "name": "Caterpillar, Inc.",
      "sector": "Industrials",
      "industry": "Farm & Heavy Construction Machinery",
      "price": 726.31,
      "market_cap": 339898236928,
      "fundamentals": {
        "trailing_pe": 38.55,
        "forward_pe": 26.16,
        "pb_ratio": 15.85,
        "ps_ratio": 5.03,
        "ev_ebitda": 26.83,
        "earnings_yield": 2.59,
        "revenue_growth": 18.0,
        "earnings_growth": -11.4,
        "growth_tier": "stable"
      },
      "technicals": {
        "sma_50": 711.45,
        "sma_200": 548.17,
        "rsi": 58.7,
        "week_52_high": 789.81,
        "week_52_low": 267.3,
        "bollinger_position": 90.04,
        "price_vs_sma50": 2.09,
        "price_vs_sma200": 32.5
      },
      "scores": {
        "per_score": 28.0,
        "pbr_score": 10,
        "psr_score": 20,
        "ev_ebitda_score": 10,
        "earnings_yield_score": 20,
        "fundamental_score": 18.4,
        "technical_score": 44.95,
        "value_score": 26.36
      },
      "grade": "D",
      "recommendation": "Avoid",
      "fetched_at": "2026-04-02T14:53:06.374676"
    },
    {
      "symbol": "LLY",
      "name": "Eli Lilly and Company",
      "sector": "Healthcare",
      "industry": "Drug Manufacturers - General",
      "price": 945.02,
      "market_cap": 845810630656,
      "fundamentals": {
        "trailing_pe": 41.25,
        "forward_pe": 22.47,
        "pb_ratio": 31.87,
        "ps_ratio": 12.98,
        "ev_ebitda": 28.06,
        "earnings_yield": 2.42,
        "revenue_growth": 42.6,
        "earnings_growth": 51.4,
        "growth_tier": "hypergrowth"
      },
      "technicals": {
        "sma_50": 996.97,
        "sma_200": 895.81,
        "rsi": 41.48,
        "week_52_high": 1133.95,
        "week_52_low": 623.78,
        "bollinger_position": 51.97,
        "price_vs_sma50": -5.21,
        "price_vs_sma200": 5.49
      },
      "scores": {
        "per_score": 34.0,
        "pbr_score": 0,
        "psr_score": 10,
        "ev_ebitda_score": 10,
        "earnings_yield_score": 0,
        "fundamental_score": 13.7,
        "technical_score": 52.82,
        "value_score": 25.44
      },
      "grade": "D",
      "recommendation": "Avoid",
      "fetched_at": "2026-04-02T14:53:01.387560"
    },
    {
      "symbol": "AMD",
      "name": "Advanced Micro Devices, Inc.",
      "sector": "Technology",
      "industry": "Semiconductors",
      "price": 212.6,
      "market_cap": 346625376256,
      "fundamentals": {
        "trailing_pe": 81.46,
        "forward_pe": 19.73,
        "pb_ratio": 5.5,
        "ps_ratio": 10.01,
        "ev_ebitda": 49.84,
        "earnings_yield": 1.23,
        "revenue_growth": 34.1,
        "earnings_growth": 217.1,
        "growth_tier": "hypergrowth"
      },
      "technicals": {
        "sma_50": 211.54,
        "sma_200": 196.86,
        "rsi": 62.62,
        "week_52_high": 267.08,
        "week_52_low": 76.48,
        "bollinger_position": 89.16,
        "price_vs_sma50": 0.5,
        "price_vs_sma200": 7.99
      },
      "scores": {
        "per_score": 42.0,
        "pbr_score": 10,
        "psr_score": 10,
        "ev_ebitda_score": 10,
        "earnings_yield_score": 0,
        "fundamental_score": 18.1,
        "technical_score": 41.86,
        "value_score": 25.23
      },
      "grade": "D",
      "recommendation": "Avoid",
      "fetched_at": "2026-04-02T14:52:53.642068"
    },
    {
      "symbol": "TSLA",
      "name": "Tesla, Inc.",
      "sector": "Consumer Cyclical",
      "industry": "Auto Manufacturers",
      "price": 365.58,
      "market_cap": 1371813969920,
      "fundamentals": {
        "trailing_pe": 341.66,
        "forward_pe": 130.08,
        "pb_ratio": 16.7,
        "ps_ratio": 14.47,
        "ev_ebitda": 133.49,
        "earnings_yield": 0.29,
        "revenue_growth": -3.1,
        "earnings_growth": -60.6,
        "growth_tier": "declining"
      },
      "technicals": {
        "sma_50": 403.58,
        "sma_200": 396.94,
        "rsi": 40.12,
        "week_52_high": 498.83,
        "week_52_low": 214.25,
        "bollinger_position": 17.38,
        "price_vs_sma50": -9.42,
        "price_vs_sma200": -7.9
      },
      "scores": {
        "per_score": 0.0,
        "pbr_score": 10,
        "psr_score": 10,
        "ev_ebitda_score": 0,
        "earnings_yield_score": 0,
        "fundamental_score": 3.5,
        "technical_score": 62.92,
        "value_score": 21.33
      },
      "grade": "D",
      "recommendation": "Avoid",
      "fetched_at": "2026-04-02T14:52:53.460305"
    }
  ],
  "statistics": {
    "total_analyzed": 60,
    "successful": 60,
    "failed": 0,
    "avg_score": 39.43,
    "max_score": 62.33,
    "min_score": 21.33,
    "grade_distribution": {
      "A+": 0,
      "A": 0,
      "B+": 2,
      "B": 9,
      "C": 18,
      "D": 31
    }
  },
  "failed_symbols": [],
  "last_updated": "2026-04-02T14:53:13.913260",
  "screening_criteria": {
    "min_score": 0,
    "symbols_count": 60
  }
}