{
  "screener_results": [
    {
      "symbol": "UPS",
      "name": "United Parcel Service, Inc.",
      "sector": "Industrials",
      "industry": "Integrated Freight & Logistics",
      "price": 97.68,
      "market_cap": 82940256256,
      "fundamentals": {
        "trailing_pe": 14.89,
        "forward_pe": 12.27,
        "pb_ratio": 5.11,
        "ps_ratio": 0.94,
        "ev_ebitda": 8.98,
        "earnings_yield": 6.72,
        "revenue_growth": -3.2,
        "earnings_growth": 4.6,
        "growth_tier": "stable"
      },
      "technicals": {
        "sma_50": 108.52,
        "sma_200": 94.47,
        "rsi": 17.8,
        "week_52_high": 123.7,
        "week_52_low": 82.0,
        "bollinger_position": 0,
        "price_vs_sma50": -9.99,
        "price_vs_sma200": 3.4
      },
      "scores": {
        "per_score": 80.0,
        "pbr_score": 10,
        "psr_score": 100,
        "ev_ebitda_score": 60,
        "earnings_yield_score": 60,
        "fundamental_score": 62.0,
        "technical_score": 81.22,
        "value_score": 67.77
      },
      "grade": "B+",
      "recommendation": "Moderate Buy",
      "fetched_at": "2026-03-09T17:46:54.556814"
    },
    {
      "symbol": "WFC",
      "name": "Wells Fargo & Company",
      "sector": "Financial Services",
      "industry": "Banks - Diversified",
      "price": 77.06,
      "market_cap": 241908842496,
      "fundamentals": {
        "trailing_pe": 12.31,
        "forward_pe": 9.73,
        "pb_ratio": 1.45,
        "ps_ratio": 3.02,
        "ev_ebitda": 0,
        "earnings_yield": 8.12,
        "revenue_growth": 5.0,
        "earnings_growth": 13.1,
        "growth_tier": "moderate_growth"
      },
      "technicals": {
        "sma_50": 89.45,
        "sma_200": 83.54,
        "rsi": 28.78,
        "week_52_high": 97.76,
        "week_52_low": 58.42,
        "bollinger_position": 0,
        "price_vs_sma50": -13.85,
        "price_vs_sma200": -7.75
      },
      "scores": {
        "per_score": 90.0,
        "pbr_score": 80,
        "psr_score": 40,
        "ev_ebitda_score": 0,
        "earnings_yield_score": 80,
        "fundamental_score": 61.0,
        "technical_score": 74.27,
        "value_score": 64.98
      },
      "grade": "B+",
      "recommendation": "Moderate Buy",
      "fetched_at": "2026-03-09T17:46:41.794568"
    },
    {
      "symbol": "BAC",
      "name": "Bank of America Corporation",
      "sector": "Financial Services",
      "industry": "Banks - Diversified",
      "price": 47.1,
      "market_cap": 343984046080,
      "fundamentals": {
        "trailing_pe": 12.36,
        "forward_pe": 9.51,
        "pb_ratio": 1.23,
        "ps_ratio": 3.2,
        "ev_ebitda": 0,
        "earnings_yield": 8.09,
        "revenue_growth": 7.2,
        "earnings_growth": 21.2,
        "growth_tier": "moderate_growth"
      },
      "technicals": {
        "sma_50": 52.97,
        "sma_200": 49.96,
        "rsi": 27.53,
        "week_52_high": 57.55,
        "week_52_low": 33.07,
        "bollinger_position": 0,
        "price_vs_sma50": -11.08,
        "price_vs_sma200": -5.71
      },
      "scores": {
        "per_score": 90.0,
        "pbr_score": 80,
        "psr_score": 40,
        "ev_ebitda_score": 0,
        "earnings_yield_score": 80,
        "fundamental_score": 61.0,
        "technical_score": 74.01,
        "value_score": 64.9
      },
      "grade": "B+",
      "recommendation": "Moderate Buy",
      "fetched_at": "2026-03-09T17:46:41.433553"
    },
    {
      "symbol": "C",
      "name": "Citigroup, Inc.",
      "sector": "Financial Services",
      "industry": "Banks - Diversified",
      "price": 102.93,
      "market_cap": 180057407488,
      "fundamentals": {
        "trailing_pe": 14.73,
        "forward_pe": 8.52,
        "pb_ratio": 0.94,
        "ps_ratio": 2.38,
        "ev_ebitda": 0,
        "earnings_yield": 6.79,
        "revenue_growth": 4.4,
        "earnings_growth": -10.8,
        "growth_tier": "declining"
      },
      "technicals": {
        "sma_50": 115.68,
        "sma_200": 99.62,
        "rsi": 33.87,
        "week_52_high": 125.16,
        "week_52_low": 55.51,
        "bollinger_position": 0,
        "price_vs_sma50": -11.02,
        "price_vs_sma200": 3.33
      },
      "scores": {
        "per_score": 86.0,
        "pbr_score": 100,
        "psr_score": 60,
        "ev_ebitda_score": 0,
        "earnings_yield_score": 60,
        "fundamental_score": 63.8,
        "technical_score": 66.53,
        "value_score": 64.62
      },
      "grade": "B+",
      "recommendation": "Moderate Buy",
      "fetched_at": "2026-03-09T17:46:44.201903"
    },
    {
      "symbol": "DIS",
      "name": "Walt Disney Company (The)",
      "sector": "Communication Services",
      "industry": "Entertainment",
      "price": 100.02,
      "market_cap": 177374167040,
      "fundamentals": {
        "trailing_pe": 14.73,
        "forward_pe": 13.6,
        "pb_ratio": 1.64,
        "ps_ratio": 1.85,
        "ev_ebitda": 11.73,
        "earnings_yield": 6.79,
        "revenue_growth": 5.2,
        "earnings_growth": -4.3,
        "growth_tier": "stable"
      },
      "technicals": {
        "sma_50": 109.0,
        "sma_200": 112.39,
        "rsi": 30.64,
        "week_52_high": 124.69,
        "week_52_low": 80.1,
        "bollinger_position": 0,
        "price_vs_sma50": -8.24,
        "price_vs_sma200": -11.01
      },
      "scores": {
        "per_score": 80.0,
        "pbr_score": 60,
        "psr_score": 80,
        "ev_ebitda_score": 40,
        "earnings_yield_score": 60,
        "fundamental_score": 65.0,
        "technical_score": 56.75,
        "value_score": 62.52
      },
      "grade": "B+",
      "recommendation": "Moderate Buy",
      "fetched_at": "2026-03-09T17:46:52.013867"
    },
    {
      "symbol": "PFE",
      "name": "Pfizer, Inc.",
      "sector": "Healthcare",
      "industry": "Drug Manufacturers - General",
      "price": 26.58,
      "market_cap": 151084122112,
      "fundamentals": {
        "trailing_pe": 19.54,
        "forward_pe": 9.39,
        "pb_ratio": 1.75,
        "ps_ratio": 2.41,
        "ev_ebitda": 8.09,
        "earnings_yield": 5.12,
        "revenue_growth": -1.2,
        "earnings_growth": 0,
        "growth_tier": "declining"
      },
      "technicals": {
        "sma_50": 26.11,
        "sma_200": 24.45,
        "rsi": 39.77,
        "week_52_high": 27.94,
        "week_52_low": 20.92,
        "bollinger_position": 13.75,
        "price_vs_sma50": 1.79,
        "price_vs_sma200": 8.73
      },
      "scores": {
        "per_score": 72.0,
        "pbr_score": 60,
        "psr_score": 60,
        "ev_ebitda_score": 60,
        "earnings_yield_score": 40,
        "fundamental_score": 60.6,
        "technical_score": 59.2,
        "value_score": 60.18
      },
      "grade": "B+",
      "recommendation": "Moderate Buy",
      "fetched_at": "2026-03-09T17:46:45.451332"
    },
    {
      "symbol": "SLB",
      "name": "SLB Limited",
      "sector": "Energy",
      "industry": "Oil & Gas Equipment & Services",
      "price": 46.08,
      "market_cap": 68912349184,
      "fundamentals": {
        "trailing_pe": 19.61,
        "forward_pe": 13.84,
        "pb_ratio": 2.64,
        "ps_ratio": 1.93,
        "ev_ebitda": 10.29,
        "earnings_yield": 5.1,
        "revenue_growth": 5.0,
        "earnings_growth": -28.6,
        "growth_tier": "declining"
      },
      "technicals": {
        "sma_50": 47.3,
        "sma_200": 37.79,
        "rsi": 29.71,
        "week_52_high": 52.45,
        "week_52_low": 31.11,
        "bollinger_position": 0,
        "price_vs_sma50": -2.56,
        "price_vs_sma200": 21.95
      },
      "scores": {
        "per_score": 66.0,
        "pbr_score": 40,
        "psr_score": 80,
        "ev_ebitda_score": 40,
        "earnings_yield_score": 40,
        "fundamental_score": 53.8,
        "technical_score": 73.79,
        "value_score": 59.8
      },
      "grade": "B",
      "recommendation": "Hold",
      "fetched_at": "2026-03-09T17:46:57.987641"
    },
    {
      "symbol": "BMY",
      "name": "Bristol-Myers Squibb Company",
      "sector": "Healthcare",
      "industry": "Drug Manufacturers - General",
      "price": 60.04,
      "market_cap": 122269884416,
      "fundamentals": {
        "trailing_pe": 17.35,
        "forward_pe": 9.8,
        "pb_ratio": 6.62,
        "ps_ratio": 2.54,
        "ev_ebitda": 8.34,
        "earnings_yield": 5.76,
        "revenue_growth": 1.3,
        "earnings_growth": 1392.1,
        "growth_tier": "hypergrowth"
      },
      "technicals": {
        "sma_50": 57.59,
        "sma_200": 49.04,
        "rsi": 48.24,
        "week_52_high": 63.33,
        "week_52_low": 42.52,
        "bollinger_position": 23.14,
        "price_vs_sma50": 4.25,
        "price_vs_sma200": 22.43
      },
      "scores": {
        "per_score": 88.0,
        "pbr_score": 10,
        "psr_score": 60,
        "ev_ebitda_score": 60,
        "earnings_yield_score": 60,
        "fundamental_score": 58.4,
        "technical_score": 51.86,
        "value_score": 56.44
      },
      "grade": "B",
      "recommendation": "Hold",
      "fetched_at": "2026-03-09T17:46:48.033339"
    },
    {
      "symbol": "PSX",
      "name": "Phillips 66",
      "sector": "Energy",
      "industry": "Oil & Gas Refining & Marketing",
      "price": 164.03,
      "market_cap": 65734041600,
      "fundamentals": {
        "trailing_pe": 15.2,
        "forward_pe": 12.91,
        "pb_ratio": 2.26,
        "ps_ratio": 0.5,
        "ev_ebitda": 13.21,
        "earnings_yield": 6.58,
        "revenue_growth": 1.3,
        "earnings_growth": 242728.4,
        "growth_tier": "hypergrowth"
      },
      "technicals": {
        "sma_50": 146.48,
        "sma_200": 131.56,
        "rsi": 64.84,
        "week_52_high": 169.62,
        "week_52_low": 91.01,
        "bollinger_position": 85.53,
        "price_vs_sma50": 11.98,
        "price_vs_sma200": 24.68
      },
      "scores": {
        "per_score": 74.0,
        "pbr_score": 40,
        "psr_score": 100,
        "ev_ebitda_score": 40,
        "earnings_yield_score": 60,
        "fundamental_score": 62.2,
        "technical_score": 37.84,
        "value_score": 54.89
      },
      "grade": "B",
      "recommendation": "Hold",
      "fetched_at": "2026-03-09T17:46:58.807870"
    },
    {
      "symbol": "UNH",
      "name": "UnitedHealth Group Incorporated",
      "sector": "Healthcare",
      "industry": "Healthcare Plans",
      "price": 281.25,
      "market_cap": 255283822592,
      "fundamentals": {
        "trailing_pe": 21.24,
        "forward_pe": 14.04,
        "pb_ratio": 2.71,
        "ps_ratio": 0.57,
        "ev_ebitda": 14.91,
        "earnings_yield": 4.71,
        "revenue_growth": 12.3,
        "earnings_growth": -99.9,
        "growth_tier": "declining"
      },
      "technicals": {
        "sma_50": 308.02,
        "sma_200": 312.62,
        "rsi": 43.34,
        "week_52_high": 606.36,
        "week_52_low": 234.6,
        "bollinger_position": 31.98,
        "price_vs_sma50": -8.69,
        "price_vs_sma200": -10.03
      },
      "scores": {
        "per_score": 52.0,
        "pbr_score": 40,
        "psr_score": 100,
        "ev_ebitda_score": 40,
        "earnings_yield_score": 40,
        "fundamental_score": 52.6,
        "technical_score": 57.13,
        "value_score": 53.96
      },
      "grade": "B",
      "recommendation": "Hold",
      "fetched_at": "2026-03-09T17:46:45.048697"
    },
    {
      "symbol": "JPM",
      "name": "JP Morgan Chase & Co.",
      "sector": "Financial Services",
      "industry": "Banks - Diversified",
      "price": 284.57,
      "market_cap": 767484231680,
      "fundamentals": {
        "trailing_pe": 14.21,
        "forward_pe": 12.11,
        "pb_ratio": 2.24,
        "ps_ratio": 4.56,
        "ev_ebitda": 0,
        "earnings_yield": 7.04,
        "revenue_growth": 2.5,
        "earnings_growth": -3.6,
        "growth_tier": "declining"
      },
      "technicals": {
        "sma_50": 310.31,
        "sma_200": 298.33,
        "rsi": 29.26,
        "week_52_high": 337.25,
        "week_52_low": 202.16,
        "bollinger_position": 0,
        "price_vs_sma50": -8.3,
        "price_vs_sma200": -4.61
      },
      "scores": {
        "per_score": 80.0,
        "pbr_score": 40,
        "psr_score": 40,
        "ev_ebitda_score": 0,
        "earnings_yield_score": 60,
        "fundamental_score": 47.0,
        "technical_score": 68.5,
        "value_score": 53.45
      },
      "grade": "B",
      "recommendation": "Hold",
      "fetched_at": "2026-03-09T17:46:41.077122"
    },
    {
      "symbol": "EOG",
      "name": "EOG Resources, Inc.",
      "sector": "Energy",
      "industry": "Oil & Gas E&P",
      "price": 132.99,
      "market_cap": 72162877440,
      "fundamentals": {
        "trailing_pe": 14.58,
        "forward_pe": 11.92,
        "pb_ratio": 2.4,
        "ps_ratio": 3.19,
        "ev_ebitda": 6.5,
        "earnings_yield": 6.86,
        "revenue_growth": 0,
        "earnings_growth": -41.7,
        "growth_tier": "declining"
      },
      "technicals": {
        "sma_50": 113.66,
        "sma_200": 112.53,
        "rsi": 78.59,
        "week_52_high": 134.36,
        "week_52_low": 101.59,
        "bollinger_position": 95.2,
        "price_vs_sma50": 17.02,
        "price_vs_sma200": 18.18
      },
      "scores": {
        "per_score": 80.0,
        "pbr_score": 40,
        "psr_score": 40,
        "ev_ebitda_score": 80,
        "earnings_yield_score": 60,
        "fundamental_score": 63.0,
        "technical_score": 30.25,
        "value_score": 53.18
      },
      "grade": "B",
      "recommendation": "Hold",
      "fetched_at": "2026-03-09T17:46:58.457386"
    },
    {
      "symbol": "GS",
      "name": "Goldman Sachs Group, Inc. (The)",
      "sector": "Financial Services",
      "industry": "Capital Markets",
      "price": 808.31,
      "market_cap": 242435211264,
      "fundamentals": {
        "trailing_pe": 15.74,
        "forward_pe": 12.43,
        "pb_ratio": 2.27,
        "ps_ratio": 4.08,
        "ev_ebitda": 0,
        "earnings_yield": 6.35,
        "revenue_growth": 15.2,
        "earnings_growth": 17.3,
        "growth_tier": "high_growth"
      },
      "technicals": {
        "sma_50": 912.19,
        "sma_200": 781.86,
        "rsi": 29.13,
        "week_52_high": 984.7,
        "week_52_low": 439.38,
        "bollinger_position": 0,
        "price_vs_sma50": -11.39,
        "price_vs_sma200": 3.38
      },
      "scores": {
        "per_score": 72.0,
        "pbr_score": 40,
        "psr_score": 40,
        "ev_ebitda_score": 0,
        "earnings_yield_score": 60,
        "fundamental_score": 44.6,
        "technical_score": 71.67,
        "value_score": 52.72
      },
      "grade": "B",
      "recommendation": "Hold",
      "fetched_at": "2026-03-09T17:46:42.105500"
    },
    {
      "symbol": "MPC",
      "name": "Marathon Petroleum Corporation",
      "sector": "Energy",
      "industry": "Oil & Gas Refining & Marketing",
      "price": 217.01,
      "market_cap": 65233739776,
      "fundamentals": {
        "trailing_pe": 16.43,
        "forward_pe": 14.8,
        "pb_ratio": 3.7,
        "ps_ratio": 0.49,
        "ev_ebitda": 10.56,
        "earnings_yield": 6.09,
        "revenue_growth": -0.5,
        "earnings_growth": 350.7,
        "growth_tier": "hypergrowth"
      },
      "technicals": {
        "sma_50": 186.66,
        "sma_200": 179.17,
        "rsi": 66.6,
        "week_52_high": 228.55,
        "week_52_low": 115.1,
        "bollinger_position": 85.98,
        "price_vs_sma50": 16.26,
        "price_vs_sma200": 21.12
      },
      "scores": {
        "per_score": 74.0,
        "pbr_score": 20,
        "psr_score": 100,
        "ev_ebitda_score": 40,
        "earnings_yield_score": 60,
        "fundamental_score": 58.2,
        "technical_score": 36.05,
        "value_score": 51.56
      },
      "grade": "B",
      "recommendation": "Hold",
      "fetched_at": "2026-03-09T17:46:59.520215"
    },
    {
      "symbol": "MS",
      "name": "Morgan Stanley",
      "sector": "Financial Services",
      "industry": "Capital Markets",
      "price": 156.99,
      "market_cap": 249278185472,
      "fundamentals": {
        "trailing_pe": 15.38,
        "forward_pe": 12.78,
        "pb_ratio": 2.44,
        "ps_ratio": 3.55,
        "ev_ebitda": 0,
        "earnings_yield": 6.5,
        "revenue_growth": 11.0,
        "earnings_growth": 20.7,
        "growth_tier": "high_growth"
      },
      "technicals": {
        "sma_50": 177.87,
        "sma_200": 157.62,
        "rsi": 36.1,
        "week_52_high": 192.68,
        "week_52_low": 94.33,
        "bollinger_position": 0,
        "price_vs_sma50": -11.74,
        "price_vs_sma200": -0.4
      },
      "scores": {
        "per_score": 72.0,
        "pbr_score": 40,
        "psr_score": 40,
        "ev_ebitda_score": 0,
        "earnings_yield_score": 60,
        "fundamental_score": 44.6,
        "technical_score": 65.71,
        "value_score": 50.93
      },
      "grade": "B",
      "recommendation": "Hold",
      "fetched_at": "2026-03-09T17:46:42.462817"
    },
    {
      "symbol": "MRK",
      "name": "Merck & Company, Inc.",
      "sector": "Healthcare",
      "industry": "Drug Manufacturers - General",
      "price": 115.63,
      "market_cap": 285882679296,
      "fundamentals": {
        "trailing_pe": 15.88,
        "forward_pe": 11.83,
        "pb_ratio": 5.44,
        "ps_ratio": 4.4,
        "ev_ebitda": 11.07,
        "earnings_yield": 6.3,
        "revenue_growth": 5.0,
        "earnings_growth": -19.3,
        "growth_tier": "declining"
      },
      "technicals": {
        "sma_50": 114.09,
        "sma_200": 92.01,
        "rsi": 35.58,
        "week_52_high": 125.14,
        "week_52_low": 73.31,
        "bollinger_position": 5.81,
        "price_vs_sma50": 1.35,
        "price_vs_sma200": 25.68
      },
      "scores": {
        "per_score": 66.0,
        "pbr_score": 10,
        "psr_score": 40,
        "ev_ebitda_score": 40,
        "earnings_yield_score": 60,
        "fundamental_score": 44.8,
        "technical_score": 63.5,
        "value_score": 50.41
      },
      "grade": "B",
      "recommendation": "Hold",
      "fetched_at": "2026-03-09T17:46:46.224743"
    },
    {
      "symbol": "COP",
      "name": "ConocoPhillips",
      "sector": "Energy",
      "industry": "Oil & Gas E&P",
      "price": 117.95,
      "market_cap": 144174907392,
      "fundamentals": {
        "trailing_pe": 18.57,
        "forward_pe": 17.33,
        "pb_ratio": 2.24,
        "ps_ratio": 2.39,
        "ev_ebitda": 6.64,
        "earnings_yield": 5.38,
        "revenue_growth": -6.8,
        "earnings_growth": -39.0,
        "growth_tier": "declining"
      },
      "technicals": {
        "sma_50": 103.6,
        "sma_200": 93.59,
        "rsi": 74.62,
        "week_52_high": 122.5,
        "week_52_low": 79.88,
        "bollinger_position": 88.99,
        "price_vs_sma50": 13.85,
        "price_vs_sma200": 26.04
      },
      "scores": {
        "per_score": 60.0,
        "pbr_score": 40,
        "psr_score": 60,
        "ev_ebitda_score": 80,
        "earnings_yield_score": 40,
        "fundamental_score": 57.0,
        "technical_score": 32.67,
        "value_score": 49.7
      },
      "grade": "C",
      "recommendation": "Weak Hold",
      "fetched_at": "2026-03-09T17:46:57.544104"
    },
    {
      "symbol": "VLO",
      "name": "Valero Energy Corporation",
      "sector": "Energy",
      "industry": "Oil & Gas Refining & Marketing",
      "price": 217.0,
      "market_cap": 66187067392,
      "fundamentals": {
        "trailing_pe": 28.67,
        "forward_pe": 15.97,
        "pb_ratio": 2.73,
        "ps_ratio": 0.57,
        "ev_ebitda": 10.14,
        "earnings_yield": 3.49,
        "revenue_growth": -2.1,
        "earnings_growth": 317.9,
        "growth_tier": "hypergrowth"
      },
      "technicals": {
        "sma_50": 191.63,
        "sma_200": 162.76,
        "rsi": 70.1,
        "week_52_high": 232.99,
        "week_52_low": 99.0,
        "bollinger_position": 75.52,
        "price_vs_sma50": 13.24,
        "price_vs_sma200": 33.33
      },
      "scores": {
        "per_score": 54.0,
        "pbr_score": 40,
        "psr_score": 100,
        "ev_ebitda_score": 40,
        "earnings_yield_score": 20,
        "fundamental_score": 50.2,
        "technical_score": 39.43,
        "value_score": 46.97
      },
      "grade": "C",
      "recommendation": "Weak Hold",
      "fetched_at": "2026-03-09T17:46:59.233648"
    },
    {
      "symbol": "AXP",
      "name": "American Express Company",
      "sector": "Financial Services",
      "industry": "Credit Services",
      "price": 297.77,
      "market_cap": 205122797568,
      "fundamentals": {
        "trailing_pe": 19.36,
        "forward_pe": 14.8,
        "pb_ratio": 6.1,
        "ps_ratio": 3.06,
        "ev_ebitda": 0,
        "earnings_yield": 5.16,
        "revenue_growth": 10.6,
        "earnings_growth": 16.6,
        "growth_tier": "moderate_growth"
      },
      "technicals": {
        "sma_50": 350.67,
        "sma_200": 333.78,
        "rsi": 25.26,
        "week_52_high": 387.49,
        "week_52_low": 220.43,
        "bollinger_position": 10.98,
        "price_vs_sma50": -15.08,
        "price_vs_sma200": -10.79
      },
      "scores": {
        "per_score": 70.0,
        "pbr_score": 10,
        "psr_score": 40,
        "ev_ebitda_score": 0,
        "earnings_yield_score": 40,
        "fundamental_score": 35.0,
        "technical_score": 73.77,
        "value_score": 46.63
      },
      "grade": "C",
      "recommendation": "Weak Hold",
      "fetched_at": "2026-03-09T17:46:43.500960"
    },
    {
      "symbol": "BLK",
      "name": "BlackRock, Inc.",
      "sector": "Financial Services",
      "industry": "Asset Management",
      "price": 946.28,
      "market_cap": 147186614272,
      "fundamentals": {
        "trailing_pe": 26.77,
        "forward_pe": 15.3,
        "pb_ratio": 2.63,
        "ps_ratio": 6.08,
        "ev_ebitda": 16.0,
        "earnings_yield": 3.74,
        "revenue_growth": 23.4,
        "earnings_growth": -31.7,
        "growth_tier": "declining"
      },
      "technicals": {
        "sma_50": 1079.8,
        "sma_200": 1073.84,
        "rsi": 24.84,
        "week_52_high": 1219.94,
        "week_52_low": 773.74,
        "bollinger_position": 0,
        "price_vs_sma50": -12.36,
        "price_vs_sma200": -11.88
      },
      "scores": {
        "per_score": 46.0,
        "pbr_score": 40,
        "psr_score": 20,
        "ev_ebitda_score": 20,
        "earnings_yield_score": 20,
        "fundamental_score": 31.8,
        "technical_score": 77.64,
        "value_score": 45.55
      },
      "grade": "C",
      "recommendation": "Weak Hold",
      "fetched_at": "2026-03-09T17:46:43.794631"
    },
    {
      "symbol": "MMM",
      "name": "3M Company",
      "sector": "Industrials",
      "industry": "Conglomerates",
      "price": 148.73,
      "market_cap": 78334771200,
      "fundamentals": {
        "trailing_pe": 24.79,
        "forward_pe": 15.82,
        "pb_ratio": 16.77,
        "ps_ratio": 3.14,
        "ev_ebitda": 14.3,
        "earnings_yield": 4.03,
        "revenue_growth": 2.0,
        "earnings_growth": -19.9,
        "growth_tier": "declining"
      },
      "technicals": {
        "sma_50": 162.73,
        "sma_200": 157.03,
        "rsi": 19.52,
        "week_52_high": 177.41,
        "week_52_low": 121.98,
        "bollinger_position": 0,
        "price_vs_sma50": -8.61,
        "price_vs_sma200": -5.29
      },
      "scores": {
        "per_score": 46.0,
        "pbr_score": 10,
        "psr_score": 40,
        "ev_ebitda_score": 40,
        "earnings_yield_score": 20,
        "fundamental_score": 32.8,
        "technical_score": 73.41,
        "value_score": 44.98
      },
      "grade": "C",
      "recommendation": "Weak Hold",
      "fetched_at": "2026-03-09T17:46:53.773888"
    },
    {
      "symbol": "XOM",
      "name": "Exxon Mobil Corporation",
      "sector": "Energy",
      "industry": "Oil & Gas Integrated",
      "price": 151.78,
      "market_cap": 632431378432,
      "fundamentals": {
        "trailing_pe": 22.65,
        "forward_pe": 17.82,
        "pb_ratio": 2.45,
        "ps_ratio": 1.95,
        "ev_ebitda": 11.4,
        "earnings_yield": 4.41,
        "revenue_growth": -1.3,
        "earnings_growth": -11.0,
        "growth_tier": "declining"
      },
      "technicals": {
        "sma_50": 138.13,
        "sma_200": 117.23,
        "rsi": 60.66,
        "week_52_high": 159.61,
        "week_52_low": 97.8,
        "bollinger_position": 66.92,
        "price_vs_sma50": 9.88,
        "price_vs_sma200": 29.48
      },
      "scores": {
        "per_score": 46.0,
        "pbr_score": 40,
        "psr_score": 80,
        "ev_ebitda_score": 40,
        "earnings_yield_score": 20,
        "fundamental_score": 44.8,
        "technical_score": 44.46,
        "value_score": 44.7
      },
      "grade": "C",
      "recommendation": "Weak Hold",
      "fetched_at": "2026-03-09T17:46:56.631381"
    },
    {
      "symbol": "PEP",
      "name": "Pepsico, Inc.",
      "sector": "Consumer Defensive",
      "industry": "Beverages - Non-Alcoholic",
      "price": 160.44,
      "market_cap": 219376058368,
      "fundamentals": {
        "trailing_pe": 26.78,
        "forward_pe": 17.57,
        "pb_ratio": 10.75,
        "ps_ratio": 2.34,
        "ev_ebitda": 14.39,
        "earnings_yield": 3.73,
        "revenue_growth": 5.6,
        "earnings_growth": 67.5,
        "growth_tier": "hypergrowth"
      },
      "technicals": {
        "sma_50": 153.57,
        "sma_200": 142.69,
        "rsi": 49.89,
        "week_52_high": 171.48,
        "week_52_low": 127.6,
        "bollinger_position": 15.21,
        "price_vs_sma50": 4.47,
        "price_vs_sma200": 12.44
      },
      "scores": {
        "per_score": 54.0,
        "pbr_score": 10,
        "psr_score": 60,
        "ev_ebitda_score": 40,
        "earnings_yield_score": 20,
        "fundamental_score": 38.2,
        "technical_score": 59.41,
        "value_score": 44.56
      },
      "grade": "C",
      "recommendation": "Weak Hold",
      "fetched_at": "2026-03-09T17:46:49.337484"
    },
    {
      "symbol": "UNP",
      "name": "Union Pacific Corporation",
      "sector": "Industrials",
      "industry": "Railroads",
      "price": 250.07,
      "market_cap": 148389412864,
      "fundamentals": {
        "trailing_pe": 20.89,
        "forward_pe": 18.52,
        "pb_ratio": 8.03,
        "ps_ratio": 6.05,
        "ev_ebitda": 14.64,
        "earnings_yield": 4.79,
        "revenue_growth": -0.6,
        "earnings_growth": 6.8,
        "growth_tier": "stable"
      },
      "technicals": {
        "sma_50": 243.77,
        "sma_200": 228.24,
        "rsi": 34.91,
        "week_52_high": 268.14,
        "week_52_low": 204.66,
        "bollinger_position": 0,
        "price_vs_sma50": 2.58,
        "price_vs_sma200": 9.57
      },
      "scores": {
        "per_score": 48.0,
        "pbr_score": 10,
        "psr_score": 20,
        "ev_ebitda_score": 40,
        "earnings_yield_score": 40,
        "fundamental_score": 33.4,
        "technical_score": 64.2,
        "value_score": 42.64
      },
      "grade": "C",
      "recommendation": "Weak Hold",
      "fetched_at": "2026-03-09T17:46:56.233450"
    },
    {
      "symbol": "OXY",
      "name": "Occidental Petroleum Corporatio",
      "sector": "Energy",
      "industry": "Oil & Gas E&P",
      "price": 55.15,
      "market_cap": 54387675136,
      "fundamentals": {
        "trailing_pe": 40.85,
        "forward_pe": 24.01,
        "pb_ratio": 1.96,
        "ps_ratio": 2.52,
        "ev_ebitda": 7.43,
        "earnings_yield": 2.45,
        "revenue_growth": 148.9,
        "earnings_growth": 0,
        "growth_tier": "hypergrowth"
      },
      "technicals": {
        "sma_50": 46.16,
        "sma_200": 43.86,
        "rsi": 82.58,
        "week_52_high": 56.34,
        "week_52_low": 34.78,
        "bollinger_position": 84.82,
        "price_vs_sma50": 19.47,
        "price_vs_sma200": 25.72
      },
      "scores": {
        "per_score": 34.0,
        "pbr_score": 60,
        "psr_score": 60,
        "ev_ebitda_score": 80,
        "earnings_yield_score": 0,
        "fundamental_score": 47.2,
        "technical_score": 31.31,
        "value_score": 42.43
      },
      "grade": "C",
      "recommendation": "Weak Hold",
      "fetched_at": "2026-03-09T17:47:00.173931"
    },
    {
      "symbol": "INTC",
      "name": "Intel Corporation",
      "sector": "Technology",
      "industry": "Semiconductors",
      "price": 44.32,
      "market_cap": 221386801152,
      "fundamentals": {
        "trailing_pe": 0,
        "forward_pe": 44.71,
        "pb_ratio": 1.94,
        "ps_ratio": 4.19,
        "ev_ebitda": 18.89,
        "earnings_yield": 0,
        "revenue_growth": -4.1,
        "earnings_growth": 0,
        "growth_tier": "declining"
      },
      "technicals": {
        "sma_50": 45.19,
        "sma_200": 33.04,
        "rsi": 44.25,
        "week_52_high": 54.6,
        "week_52_low": 17.67,
        "bollinger_position": 28.54,
        "price_vs_sma50": -1.93,
        "price_vs_sma200": 34.15
      },
      "scores": {
        "per_score": 41.0,
        "pbr_score": 60,
        "psr_score": 40,
        "ev_ebitda_score": 20,
        "earnings_yield_score": 0,
        "fundamental_score": 34.3,
        "technical_score": 60.0,
        "value_score": 42.01
      },
      "grade": "C",
      "recommendation": "Weak Hold",
      "fetched_at": "2026-03-09T17:46:40.429778"
    },
    {
      "symbol": "TMO",
      "name": "Thermo Fisher Scientific Inc",
      "sector": "Healthcare",
      "industry": "Diagnostics & Research",
      "price": 498.55,
      "market_cap": 185203474432,
      "fundamentals": {
        "trailing_pe": 28.13,
        "forward_pe": 18.54,
        "pb_ratio": 3.51,
        "ps_ratio": 4.16,
        "ev_ebitda": 19.56,
        "earnings_yield": 3.55,
        "revenue_growth": 7.2,
        "earnings_growth": 9.3,
        "growth_tier": "moderate_growth"
      },
      "technicals": {
        "sma_50": 566.4,
        "sma_200": 510.96,
        "rsi": 48.04,
        "week_52_high": 643.99,
        "week_52_low": 385.46,
        "bollinger_position": 14.15,
        "price_vs_sma50": -11.98,
        "price_vs_sma200": -2.43
      },
      "scores": {
        "per_score": 50.0,
        "pbr_score": 20,
        "psr_score": 40,
        "ev_ebitda_score": 20,
        "earnings_yield_score": 20,
        "fundamental_score": 32.0,
        "technical_score": 65.21,
        "value_score": 41.96
      },
      "grade": "C",
      "recommendation": "Weak Hold",
      "fetched_at": "2026-03-09T17:46:46.567232"
    },
    {
      "symbol": "DHR",
      "name": "Danaher Corporation",
      "sector": "Healthcare",
      "industry": "Diagnostics & Research",
      "price": 195.6,
      "market_cap": 138316464128,
      "fundamentals": {
        "trailing_pe": 38.96,
        "forward_pe": 21.46,
        "pb_ratio": 2.63,
        "ps_ratio": 5.63,
        "ev_ebitda": 19.57,
        "earnings_yield": 2.57,
        "revenue_growth": 4.6,
        "earnings_growth": 12.5,
        "growth_tier": "moderate_growth"
      },
      "technicals": {
        "sma_50": 222.15,
        "sma_200": 209.75,
        "rsi": 30.95,
        "week_52_high": 242.8,
        "week_52_low": 171.0,
        "bollinger_position": 0,
        "price_vs_sma50": -11.95,
        "price_vs_sma200": -6.75
      },
      "scores": {
        "per_score": 30.0,
        "pbr_score": 40,
        "psr_score": 20,
        "ev_ebitda_score": 20,
        "earnings_yield_score": 20,
        "fundamental_score": 27.0,
        "technical_score": 73.98,
        "value_score": 41.09
      },
      "grade": "C",
      "recommendation": "Weak Hold",
      "fetched_at": "2026-03-09T17:46:47.276839"
    },
    {
      "symbol": "CRM",
      "name": "Salesforce, Inc.",
      "sector": "Technology",
      "industry": "Software - Application",
      "price": 196.37,
      "market_cap": 183994007552,
      "fundamentals": {
        "trailing_pe": 25.18,
        "forward_pe": 13.17,
        "pb_ratio": 3.08,
        "ps_ratio": 4.43,
        "ev_ebitda": 15.52,
        "earnings_yield": 3.97,
        "revenue_growth": 12.1,
        "earnings_growth": 17.9,
        "growth_tier": "high_growth"
      },
      "technicals": {
        "sma_50": 218.16,
        "sma_200": 243.87,
        "rsi": 59.77,
        "week_52_high": 296.05,
        "week_52_low": 174.57,
        "bollinger_position": 71.11,
        "price_vs_sma50": -9.99,
        "price_vs_sma200": -19.48
      },
      "scores": {
        "per_score": 64.0,
        "pbr_score": 20,
        "psr_score": 40,
        "ev_ebitda_score": 20,
        "earnings_yield_score": 20,
        "fundamental_score": 36.2,
        "technical_score": 49.86,
        "value_score": 40.3
      },
      "grade": "C",
      "recommendation": "Weak Hold",
      "fetched_at": "2026-03-09T17:46:40.708628"
    },
    {
      "symbol": "NKE",
      "name": "Nike, Inc.",
      "sector": "Consumer Cyclical",
      "industry": "Footwear & Accessories",
      "price": 55.74,
      "market_cap": 82509168640,
      "fundamentals": {
        "trailing_pe": 32.59,
        "forward_pe": 24.14,
        "pb_ratio": 5.86,
        "ps_ratio": 1.77,
        "ev_ebitda": 22.93,
        "earnings_yield": 3.07,
        "revenue_growth": 0.6,
        "earnings_growth": -32.1,
        "growth_tier": "declining"
      },
      "technicals": {
        "sma_50": 62.62,
        "sma_200": 66.47,
        "rsi": 17.47,
        "week_52_high": 80.19,
        "week_52_low": 52.28,
        "bollinger_position": 0,
        "price_vs_sma50": -10.99,
        "price_vs_sma200": -16.14
      },
      "scores": {
        "per_score": 26.0,
        "pbr_score": 10,
        "psr_score": 80,
        "ev_ebitda_score": 10,
        "earnings_yield_score": 20,
        "fundamental_score": 26.8,
        "technical_score": 71.05,
        "value_score": 40.07
      },
      "grade": "C",
      "recommendation": "Weak Hold",
      "fetched_at": "2026-03-09T17:46:51.225255"
    },
    {
      "symbol": "HD",
      "name": "Home Depot, Inc. (The)",
      "sector": "Consumer Cyclical",
      "industry": "Home Improvement Retail",
      "price": 347.45,
      "market_cap": 345895436288,
      "fundamentals": {
        "trailing_pe": 24.38,
        "forward_pe": 21.3,
        "pb_ratio": 26.93,
        "ps_ratio": 2.1,
        "ev_ebitda": 16.77,
        "earnings_yield": 4.1,
        "revenue_growth": -3.8,
        "earnings_growth": -14.5,
        "growth_tier": "declining"
      },
      "technicals": {
        "sma_50": 372.23,
        "sma_200": 373.94,
        "rsi": 26.12,
        "week_52_high": 426.75,
        "week_52_low": 326.31,
        "bollinger_position": 0,
        "price_vs_sma50": -6.65,
        "price_vs_sma200": -7.08
      },
      "scores": {
        "per_score": 40.0,
        "pbr_score": 0,
        "psr_score": 60,
        "ev_ebitda_score": 20,
        "earnings_yield_score": 20,
        "fundamental_score": 28.0,
        "technical_score": 67.39,
        "value_score": 39.82
      },
      "grade": "D",
      "recommendation": "Avoid",
      "fetched_at": "2026-03-09T17:46:50.345771"
    },
    {
      "symbol": "ABT",
      "name": "Abbott Laboratories",
      "sector": "Healthcare",
      "industry": "Medical Devices",
      "price": 111.66,
      "market_cap": 194029682688,
      "fundamentals": {
        "trailing_pe": 29.94,
        "forward_pe": 17.88,
        "pb_ratio": 3.72,
        "ps_ratio": 4.38,
        "ev_ebitda": 16.31,
        "earnings_yield": 3.34,
        "revenue_growth": 4.4,
        "earnings_growth": -80.9,
        "growth_tier": "declining"
      },
      "technicals": {
        "sma_50": 115.95,
        "sma_200": 125.81,
        "rsi": 48.19,
        "week_52_high": 139.15,
        "week_52_low": 105.27,
        "bollinger_position": 29.78,
        "price_vs_sma50": -3.7,
        "price_vs_sma200": -11.25
      },
      "scores": {
        "per_score": 46.0,
        "pbr_score": 20,
        "psr_score": 40,
        "ev_ebitda_score": 20,
        "earnings_yield_score": 20,
        "fundamental_score": 30.8,
        "technical_score": 55.54,
        "value_score": 38.22
      },
      "grade": "D",
      "recommendation": "Avoid",
      "fetched_at": "2026-03-09T17:46:46.947260"
    },
    {
      "symbol": "CVX",
      "name": "Chevron Corporation",
      "sector": "Energy",
      "industry": "Oil & Gas Integrated",
      "price": 190.19,
      "market_cap": 380257075200,
      "fundamentals": {
        "trailing_pe": 28.69,
        "forward_pe": 20.45,
        "pb_ratio": 2.02,
        "ps_ratio": 2.06,
        "ev_ebitda": 11.3,
        "earnings_yield": 3.49,
        "revenue_growth": -8.2,
        "earnings_growth": -23.8,
        "growth_tier": "declining"
      },
      "technicals": {
        "sma_50": 172.03,
        "sma_200": 154.02,
        "rsi": 73.13,
        "week_52_high": 192.41,
        "week_52_low": 132.04,
        "bollinger_position": 90.13,
        "price_vs_sma50": 10.56,
        "price_vs_sma200": 23.48
      },
      "scores": {
        "per_score": 40.0,
        "pbr_score": 40,
        "psr_score": 60,
        "ev_ebitda_score": 40,
        "earnings_yield_score": 20,
        "fundamental_score": 40.0,
        "technical_score": 32.92,
        "value_score": 37.88
      },
      "grade": "D",
      "recommendation": "Avoid",
      "fetched_at": "2026-03-09T17:46:57.075554"
    },
    {
      "symbol": "JNJ",
      "name": "Johnson & Johnson",
      "sector": "Healthcare",
      "industry": "Drug Manufacturers - General",
      "price": 242.21,
      "market_cap": 583713685504,
      "fundamentals": {
        "trailing_pe": 21.96,
        "forward_pe": 19.28,
        "pb_ratio": 7.15,
        "ps_ratio": 6.2,
        "ev_ebitda": 17.99,
        "earnings_yield": 4.55,
        "revenue_growth": 9.1,
        "earnings_growth": 48.6,
        "growth_tier": "hypergrowth"
      },
      "technicals": {
        "sma_50": 227.17,
        "sma_200": 188.63,
        "rsi": 50.26,
        "week_52_high": 251.71,
        "week_52_low": 141.5,
        "bollinger_position": 42.82,
        "price_vs_sma50": 6.62,
        "price_vs_sma200": 28.41
      },
      "scores": {
        "per_score": 54.0,
        "pbr_score": 10,
        "psr_score": 20,
        "ev_ebitda_score": 20,
        "earnings_yield_score": 40,
        "fundamental_score": 31.2,
        "technical_score": 50.11,
        "value_score": 36.87
      },
      "grade": "D",
      "recommendation": "Avoid",
      "fetched_at": "2026-03-09T17:46:44.647404"
    },
    {
      "symbol": "PG",
      "name": "Procter & Gamble Company (The)",
      "sector": "Consumer Defensive",
      "industry": "Household & Personal Products",
      "price": 154.52,
      "market_cap": 361651798016,
      "fundamentals": {
        "trailing_pe": 22.93,
        "forward_pe": 21.08,
        "pb_ratio": 6.87,
        "ps_ratio": 4.24,
        "ev_ebitda": 15.5,
        "earnings_yield": 4.36,
        "revenue_growth": 1.5,
        "earnings_growth": -5.4,
        "growth_tier": "declining"
      },
      "technicals": {
        "sma_50": 151.87,
        "sma_200": 151.93,
        "rsi": 41.96,
        "week_52_high": 179.99,
        "week_52_low": 137.62,
        "bollinger_position": 12.48,
        "price_vs_sma50": 1.74,
        "price_vs_sma200": 1.71
      },
      "scores": {
        "per_score": 40.0,
        "pbr_score": 10,
        "psr_score": 40,
        "ev_ebitda_score": 20,
        "earnings_yield_score": 20,
        "fundamental_score": 27.0,
        "technical_score": 57.49,
        "value_score": 36.15
      },
      "grade": "D",
      "recommendation": "Avoid",
      "fetched_at": "2026-03-09T17:46:48.461691"
    },
    {
      "symbol": "CAT",
      "name": "Caterpillar, Inc.",
      "sector": "Industrials",
      "industry": "Farm & Heavy Construction Machinery",
      "price": 689.43,
      "market_cap": 322639167488,
      "fundamentals": {
        "trailing_pe": 36.69,
        "forward_pe": 24.92,
        "pb_ratio": 15.05,
        "ps_ratio": 4.77,
        "ev_ebitda": 25.18,
        "earnings_yield": 2.73,
        "revenue_growth": 18.0,
        "earnings_growth": -11.4,
        "growth_tier": "stable"
      },
      "technicals": {
        "sma_50": 678.22,
        "sma_200": 516.24,
        "rsi": 28.05,
        "week_52_high": 789.81,
        "week_52_low": 267.3,
        "bollinger_position": 0,
        "price_vs_sma50": 1.65,
        "price_vs_sma200": 33.55
      },
      "scores": {
        "per_score": 28.0,
        "pbr_score": 10,
        "psr_score": 40,
        "ev_ebitda_score": 10,
        "earnings_yield_score": 20,
        "fundamental_score": 21.4,
        "technical_score": 70.0,
        "value_score": 35.98
      },
      "grade": "D",
      "recommendation": "Avoid",
      "fetched_at": "2026-03-09T17:46:52.446848"
    },
    {
      "symbol": "AMZN",
      "name": "Amazon.com, Inc.",
      "sector": "Consumer Cyclical",
      "industry": "Internet Retail",
      "price": 209.15,
      "market_cap": 2245208571904,
      "fundamentals": {
        "trailing_pe": 29.21,
        "forward_pe": 22.4,
        "pb_ratio": 5.46,
        "ps_ratio": 3.13,
        "ev_ebitda": 16.09,
        "earnings_yield": 3.42,
        "revenue_growth": 13.6,
        "earnings_growth": 5.0,
        "growth_tier": "moderate_growth"
      },
      "technicals": {
        "sma_50": 224.93,
        "sma_200": 224.51,
        "rsi": 58.71,
        "week_52_high": 258.6,
        "week_52_low": 161.38,
        "bollinger_position": 56.65,
        "price_vs_sma50": -7.01,
        "price_vs_sma200": -6.84
      },
      "scores": {
        "per_score": 40.0,
        "pbr_score": 10,
        "psr_score": 40,
        "ev_ebitda_score": 20,
        "earnings_yield_score": 20,
        "fundamental_score": 27.0,
        "technical_score": 55.05,
        "value_score": 35.41
      },
      "grade": "D",
      "recommendation": "Avoid",
      "fetched_at": "2026-03-09T17:46:39.065753"
    },
    {
      "symbol": "WMT",
      "name": "Walmart Inc.",
      "sector": "Consumer Defensive",
      "industry": "Discount Stores",
      "price": 123.08,
      "market_cap": 981298511872,
      "fundamentals": {
        "trailing_pe": 44.92,
        "forward_pe": 37.4,
        "pb_ratio": 9.85,
        "ps_ratio": 1.38,
        "ev_ebitda": 23.76,
        "earnings_yield": 2.23,
        "revenue_growth": 5.6,
        "earnings_growth": -19.0,
        "growth_tier": "declining"
      },
      "technicals": {
        "sma_50": 121.5,
        "sma_200": 106.67,
        "rsi": 37.43,
        "week_52_high": 134.69,
        "week_52_low": 79.81,
        "bollinger_position": 17.21,
        "price_vs_sma50": 1.3,
        "price_vs_sma200": 15.39
      },
      "scores": {
        "per_score": 20.0,
        "pbr_score": 10,
        "psr_score": 80,
        "ev_ebitda_score": 10,
        "earnings_yield_score": 0,
        "fundamental_score": 22.0,
        "technical_score": 65.98,
        "value_score": 35.19
      },
      "grade": "D",
      "recommendation": "Avoid",
      "fetched_at": "2026-03-09T17:46:49.721637"
    },
    {
      "symbol": "META",
      "name": "Meta Platforms, Inc.",
      "sector": "Communication Services",
      "industry": "Internet Content & Information",
      "price": 634.23,
      "market_cap": 1604332552192,
      "fundamentals": {
        "trailing_pe": 27.02,
        "forward_pe": 17.68,
        "pb_ratio": 7.39,
        "ps_ratio": 7.98,
        "ev_ebitda": 16.04,
        "earnings_yield": 3.7,
        "revenue_growth": 23.8,
        "earnings_growth": 10.7,
        "growth_tier": "high_growth"
      },
      "technicals": {
        "sma_50": 655.89,
        "sma_200": 690.83,
        "rsi": 47.83,
        "week_52_high": 796.25,
        "week_52_low": 479.8,
        "bollinger_position": 12.69,
        "price_vs_sma50": -3.3,
        "price_vs_sma200": -8.19
      },
      "scores": {
        "per_score": 52.0,
        "pbr_score": 10,
        "psr_score": 20,
        "ev_ebitda_score": 20,
        "earnings_yield_score": 20,
        "fundamental_score": 27.6,
        "technical_score": 51.24,
        "value_score": 34.69
      },
      "grade": "D",
      "recommendation": "Avoid",
      "fetched_at": "2026-03-09T17:46:39.344808"
    },
    {
      "symbol": "KO",
      "name": "Coca-Cola Company (The)",
      "sector": "Consumer Defensive",
      "industry": "Beverages - Non-Alcoholic",
      "price": 77.39,
      "market_cap": 332880019456,
      "fundamentals": {
        "trailing_pe": 25.46,
        "forward_pe": 22.33,
        "pb_ratio": 10.35,
        "ps_ratio": 6.94,
        "ev_ebitda": 22.74,
        "earnings_yield": 3.93,
        "revenue_growth": 2.4,
        "earnings_growth": 3.6,
        "growth_tier": "stable"
      },
      "technicals": {
        "sma_50": 74.83,
        "sma_200": 70.3,
        "rsi": 37.48,
        "week_52_high": 82.0,
        "week_52_low": 65.35,
        "bollinger_position": 18.39,
        "price_vs_sma50": 3.42,
        "price_vs_sma200": 10.08
      },
      "scores": {
        "per_score": 40.0,
        "pbr_score": 10,
        "psr_score": 20,
        "ev_ebitda_score": 10,
        "earnings_yield_score": 20,
        "fundamental_score": 22.0,
        "technical_score": 64.11,
        "value_score": 34.63
      },
      "grade": "D",
      "recommendation": "Avoid",
      "fetched_at": "2026-03-09T17:46:48.891177"
    },
    {
      "symbol": "KMI",
      "name": "Kinder Morgan, Inc.",
      "sector": "Energy",
      "industry": "Oil & Gas Midstream",
      "price": 33.33,
      "market_cap": 74141671424,
      "fundamentals": {
        "trailing_pe": 24.32,
        "forward_pe": 22.74,
        "pb_ratio": 2.38,
        "ps_ratio": 4.38,
        "ev_ebitda": 15.22,
        "earnings_yield": 4.11,
        "revenue_growth": 13.1,
        "earnings_growth": 49.3,
        "growth_tier": "hypergrowth"
      },
      "technicals": {
        "sma_50": 30.16,
        "sma_200": 27.8,
        "rsi": 70.43,
        "week_52_high": 34.24,
        "week_52_low": 23.94,
        "bollinger_position": 68.1,
        "price_vs_sma50": 10.5,
        "price_vs_sma200": 19.87
      },
      "scores": {
        "per_score": 40.0,
        "pbr_score": 40,
        "psr_score": 40,
        "ev_ebitda_score": 20,
        "earnings_yield_score": 20,
        "fundamental_score": 33.0,
        "technical_score": 37.12,
        "value_score": 34.24
      },
      "grade": "D",
      "recommendation": "Avoid",
      "fetched_at": "2026-03-09T17:47:00.499718"
    },
    {
      "symbol": "GOOGL",
      "name": "Alphabet Inc.",
      "sector": "Communication Services",
      "industry": "Internet Content & Information",
      "price": 301.48,
      "market_cap": 3647063982080,
      "fundamentals": {
        "trailing_pe": 27.89,
        "forward_pe": 22.46,
        "pb_ratio": 8.78,
        "ps_ratio": 9.05,
        "ev_ebitda": 23.65,
        "earnings_yield": 3.59,
        "revenue_growth": 18.0,
        "earnings_growth": 31.1,
        "growth_tier": "high_growth"
      },
      "technicals": {
        "sma_50": 319.53,
        "sma_200": 253.57,
        "rsi": 49.42,
        "week_52_high": 349.0,
        "week_52_low": 140.53,
        "bollinger_position": 24.4,
        "price_vs_sma50": -5.65,
        "price_vs_sma200": 18.9
      },
      "scores": {
        "per_score": 40.0,
        "pbr_score": 10,
        "psr_score": 20,
        "ev_ebitda_score": 10,
        "earnings_yield_score": 20,
        "fundamental_score": 22.0,
        "technical_score": 59.0,
        "value_score": 33.1
      },
      "grade": "D",
      "recommendation": "Avoid",
      "fetched_at": "2026-03-09T17:46:38.837570"
    },
    {
      "symbol": "V",
      "name": "Visa Inc.",
      "sector": "Financial Services",
      "industry": "Credit Services",
      "price": 311.33,
      "market_cap": 600256544768,
      "fundamentals": {
        "trailing_pe": 29.21,
        "forward_pe": 21.43,
        "pb_ratio": 15.54,
        "ps_ratio": 14.5,
        "ev_ebitda": 21.05,
        "earnings_yield": 3.42,
        "revenue_growth": 14.6,
        "earnings_growth": 17.4,
        "growth_tier": "high_growth"
      },
      "technicals": {
        "sma_50": 329.72,
        "sma_200": 340.59,
        "rsi": 40.37,
        "week_52_high": 375.51,
        "week_52_low": 299.0,
        "bollinger_position": 18.51,
        "price_vs_sma50": -5.58,
        "price_vs_sma200": -8.59
      },
      "scores": {
        "per_score": 40.0,
        "pbr_score": 10,
        "psr_score": 10,
        "ev_ebitda_score": 10,
        "earnings_yield_score": 20,
        "fundamental_score": 20.5,
        "technical_score": 61.7,
        "value_score": 32.86
      },
      "grade": "D",
      "recommendation": "Avoid",
      "fetched_at": "2026-03-09T17:46:42.744694"
    },
    {
      "symbol": "HON",
      "name": "Honeywell International Inc.",
      "sector": "Industrials",
      "industry": "Conglomerates",
      "price": 234.24,
      "market_cap": 157843865600,
      "fundamentals": {
        "trailing_pe": 30.9,
        "forward_pe": 20.38,
        "pb_ratio": 10.7,
        "ps_ratio": 4.22,
        "ev_ebitda": 20.47,
        "earnings_yield": 3.24,
        "revenue_growth": -3.3,
        "earnings_growth": -76.4,
        "growth_tier": "declining"
      },
      "technicals": {
        "sma_50": 224.17,
        "sma_200": 207.41,
        "rsi": 39.87,
        "week_52_high": 248.18,
        "week_52_low": 169.05,
        "bollinger_position": 0,
        "price_vs_sma50": 4.49,
        "price_vs_sma200": 12.93
      },
      "scores": {
        "per_score": 26.0,
        "pbr_score": 10,
        "psr_score": 40,
        "ev_ebitda_score": 10,
        "earnings_yield_score": 20,
        "fundamental_score": 20.8,
        "technical_score": 59.52,
        "value_score": 32.42
      },
      "grade": "D",
      "recommendation": "Avoid",
      "fetched_at": "2026-03-09T17:46:54.237341"
    },
    {
      "symbol": "AAPL",
      "name": "Apple Inc.",
      "sector": "Technology",
      "industry": "Consumer Electronics",
      "price": 256.24,
      "market_cap": 3766196371456,
      "fundamentals": {
        "trailing_pe": 32.44,
        "forward_pe": 27.58,
        "pb_ratio": 42.72,
        "ps_ratio": 8.65,
        "ev_ebitda": 24.88,
        "earnings_yield": 3.08,
        "revenue_growth": 15.7,
        "earnings_growth": 18.3,
        "growth_tier": "high_growth"
      },
      "technicals": {
        "sma_50": 263.82,
        "sma_200": 244.02,
        "rsi": 39.66,
        "week_52_high": 288.62,
        "week_52_low": 169.21,
        "bollinger_position": 12.47,
        "price_vs_sma50": -2.87,
        "price_vs_sma200": 5.01
      },
      "scores": {
        "per_score": 32.0,
        "pbr_score": 0,
        "psr_score": 20,
        "ev_ebitda_score": 10,
        "earnings_yield_score": 20,
        "fundamental_score": 17.6,
        "technical_score": 64.53,
        "value_score": 31.68
      },
      "grade": "D",
      "recommendation": "Avoid",
      "fetched_at": "2026-03-09T17:46:38.352156"
    },
    {
      "symbol": "NVDA",
      "name": "NVIDIA Corporation",
      "sector": "Technology",
      "industry": "Semiconductors",
      "price": 179.27,
      "market_cap": 4356914282496,
      "fundamentals": {
        "trailing_pe": 36.51,
        "forward_pe": 16.61,
        "pb_ratio": 27.7,
        "ps_ratio": 20.18,
        "ev_ebitda": 32.05,
        "earnings_yield": 2.74,
        "revenue_growth": 73.2,
        "earnings_growth": 95.6,
        "growth_tier": "hypergrowth"
      },
      "technicals": {
        "sma_50": 185.81,
        "sma_200": 176.35,
        "rsi": 43.95,
        "week_52_high": 212.19,
        "week_52_low": 86.62,
        "bollinger_position": 16.97,
        "price_vs_sma50": -3.52,
        "price_vs_sma200": 1.66
      },
      "scores": {
        "per_score": 48.0,
        "pbr_score": 0,
        "psr_score": 0,
        "ev_ebitda_score": 10,
        "earnings_yield_score": 20,
        "fundamental_score": 19.4,
        "technical_score": 58.84,
        "value_score": 31.23
      },
      "grade": "D",
      "recommendation": "Avoid",
      "fetched_at": "2026-03-09T17:46:39.569726"
    },
    {
      "symbol": "DE",
      "name": "Deere & Company",
      "sector": "Industrials",
      "industry": "Farm & Heavy Construction Machinery",
      "price": 590.75,
      "market_cap": 159565889536,
      "fundamentals": {
        "trailing_pe": 33.28,
        "forward_pe": 25.54,
        "pb_ratio": 6.07,
        "ps_ratio": 3.41,
        "ev_ebitda": 25.3,
        "earnings_yield": 3.0,
        "revenue_growth": 13.0,
        "earnings_growth": -24.1,
        "growth_tier": "declining"
      },
      "technicals": {
        "sma_50": 550.97,
        "sma_200": 501.08,
        "rsi": 47.09,
        "week_52_high": 674.19,
        "week_52_low": 404.42,
        "bollinger_position": 23.78,
        "price_vs_sma50": 7.22,
        "price_vs_sma200": 17.9
      },
      "scores": {
        "per_score": 26.0,
        "pbr_score": 10,
        "psr_score": 40,
        "ev_ebitda_score": 10,
        "earnings_yield_score": 20,
        "fundamental_score": 20.8,
        "technical_score": 54.99,
        "value_score": 31.06
      },
      "grade": "D",
      "recommendation": "Avoid",
      "fetched_at": "2026-03-09T17:46:55.876691"
    },
    {
      "symbol": "MCD",
      "name": "McDonald's Corporation",
      "sector": "Consumer Cyclical",
      "industry": "Restaurants",
      "price": 328.87,
      "market_cap": 234683088896,
      "fundamentals": {
        "trailing_pe": 27.54,
        "forward_pe": 22.97,
        "pb_ratio": -130.56,
        "ps_ratio": 8.73,
        "ev_ebitda": 19.67,
        "earnings_yield": 3.63,
        "revenue_growth": 9.7,
        "earnings_growth": 8.2,
        "growth_tier": "moderate_growth"
      },
      "technicals": {
        "sma_50": 316.91,
        "sma_200": 304.61,
        "rsi": 54.93,
        "week_52_high": 341.75,
        "week_52_low": 283.47,
        "bollinger_position": 49.79,
        "price_vs_sma50": 3.77,
        "price_vs_sma200": 7.96
      },
      "scores": {
        "per_score": 40.0,
        "pbr_score": 0,
        "psr_score": 20,
        "ev_ebitda_score": 20,
        "earnings_yield_score": 20,
        "fundamental_score": 22.0,
        "technical_score": 51.01,
        "value_score": 30.7
      },
      "grade": "D",
      "recommendation": "Avoid",
      "fetched_at": "2026-03-09T17:46:50.828220"
    },
    {
      "symbol": "BA",
      "name": "Boeing Company (The)",
      "sector": "Industrials",
      "industry": "Aerospace & Defense",
      "price": 222.99,
      "market_cap": 175124545536,
      "fundamentals": {
        "trailing_pe": 90.28,
        "forward_pe": 47.41,
        "pb_ratio": 32.12,
        "ps_ratio": 1.96,
        "ev_ebitda": -64.61,
        "earnings_yield": 1.11,
        "revenue_growth": 57.1,
        "earnings_growth": 0,
        "growth_tier": "hypergrowth"
      },
      "technicals": {
        "sma_50": 234.71,
        "sma_200": 219.01,
        "rsi": 31.15,
        "week_52_high": 254.35,
        "week_52_low": 128.88,
        "bollinger_position": 12.92,
        "price_vs_sma50": -5.0,
        "price_vs_sma200": 1.82
      },
      "scores": {
        "per_score": 14.0,
        "pbr_score": 0,
        "psr_score": 80,
        "ev_ebitda_score": 0,
        "earnings_yield_score": 0,
        "fundamental_score": 16.2,
        "technical_score": 64.29,
        "value_score": 30.63
      },
      "grade": "D",
      "recommendation": "Avoid",
      "fetched_at": "2026-03-09T17:46:52.853375"
    },
    {
      "symbol": "AMD",
      "name": "Advanced Micro Devices, Inc.",
      "sector": "Technology",
      "industry": "Semiconductors",
      "price": 196.09,
      "market_cap": 319731728384,
      "fundamentals": {
        "trailing_pe": 74.85,
        "forward_pe": 18.02,
        "pb_ratio": 5.07,
        "ps_ratio": 9.23,
        "ev_ebitda": 45.54,
        "earnings_yield": 1.34,
        "revenue_growth": 34.1,
        "earnings_growth": 217.1,
        "growth_tier": "hypergrowth"
      },
      "technicals": {
        "sma_50": 217.23,
        "sma_200": 189.03,
        "rsi": 45.49,
        "week_52_high": 267.08,
        "week_52_low": 76.48,
        "bollinger_position": 24.16,
        "price_vs_sma50": -9.73,
        "price_vs_sma200": 3.74
      },
      "scores": {
        "per_score": 42.0,
        "pbr_score": 10,
        "psr_score": 20,
        "ev_ebitda_score": 10,
        "earnings_yield_score": 0,
        "fundamental_score": 19.6,
        "technical_score": 56.23,
        "value_score": 30.59
      },
      "grade": "D",
      "recommendation": "Avoid",
      "fetched_at": "2026-03-09T17:46:40.081118"
    },
    {
      "symbol": "MSFT",
      "name": "Microsoft Corporation",
      "sector": "Technology",
      "industry": "Software - Infrastructure",
      "price": 404.97,
      "market_cap": 3009875017728,
      "fundamentals": {
        "trailing_pe": 25.33,
        "forward_pe": 21.49,
        "pb_ratio": 7.7,
        "ps_ratio": 9.85,
        "ev_ebitda": 17.52,
        "earnings_yield": 3.95,
        "revenue_growth": 16.7,
        "earnings_growth": 59.8,
        "growth_tier": "hypergrowth"
      },
      "technicals": {
        "sma_50": 435.36,
        "sma_200": 482.39,
        "rsi": 56.74,
        "week_52_high": 555.45,
        "week_52_low": 344.79,
        "bollinger_position": 63.78,
        "price_vs_sma50": -6.98,
        "price_vs_sma200": -16.05
      },
      "scores": {
        "per_score": 40.0,
        "pbr_score": 10,
        "psr_score": 20,
        "ev_ebitda_score": 20,
        "earnings_yield_score": 20,
        "fundamental_score": 24.0,
        "technical_score": 45.06,
        "value_score": 30.32
      },
      "grade": "D",
      "recommendation": "Avoid",
      "fetched_at": "2026-03-09T17:46:38.605185"
    },
    {
      "symbol": "LMT",
      "name": "Lockheed Martin Corporation",
      "sector": "Industrials",
      "industry": "Aerospace & Defense",
      "price": 671.15,
      "market_cap": 155301478400,
      "fundamentals": {
        "trailing_pe": 31.22,
        "forward_pe": 21.0,
        "pb_ratio": 22.87,
        "ps_ratio": 2.07,
        "ev_ebitda": 20.91,
        "earnings_yield": 3.2,
        "revenue_growth": 9.1,
        "earnings_growth": 161.0,
        "growth_tier": "hypergrowth"
      },
      "technicals": {
        "sma_50": 595.84,
        "sma_200": 493.43,
        "rsi": 59.5,
        "week_52_high": 692.0,
        "week_52_low": 410.11,
        "bollinger_position": 82.33,
        "price_vs_sma50": 12.64,
        "price_vs_sma200": 36.02
      },
      "scores": {
        "per_score": 34.0,
        "pbr_score": 0,
        "psr_score": 60,
        "ev_ebitda_score": 10,
        "earnings_yield_score": 20,
        "fundamental_score": 24.2,
        "technical_score": 42.69,
        "value_score": 29.75
      },
      "grade": "D",
      "recommendation": "Avoid",
      "fetched_at": "2026-03-09T17:46:55.464394"
    },
    {
      "symbol": "ABBV",
      "name": "AbbVie Inc.",
      "sector": "Healthcare",
      "industry": "Drug Manufacturers - General",
      "price": 225.3,
      "market_cap": 398368473088,
      "fundamentals": {
        "trailing_pe": 95.06,
        "forward_pe": 13.98,
        "pb_ratio": -121.78,
        "ps_ratio": 6.51,
        "ev_ebitda": 16.07,
        "earnings_yield": 1.05,
        "revenue_growth": 10.0,
        "earnings_growth": 0,
        "growth_tier": "moderate_growth"
      },
      "technicals": {
        "sma_50": 224.44,
        "sma_200": 211.35,
        "rsi": 40.92,
        "week_52_high": 244.81,
        "week_52_low": 164.39,
        "bollinger_position": 31.18,
        "price_vs_sma50": 0.38,
        "price_vs_sma200": 6.6
      },
      "scores": {
        "per_score": 40.0,
        "pbr_score": 0,
        "psr_score": 20,
        "ev_ebitda_score": 20,
        "earnings_yield_score": 0,
        "fundamental_score": 19.0,
        "technical_score": 54.05,
        "value_score": 29.52
      },
      "grade": "D",
      "recommendation": "Avoid",
      "fetched_at": "2026-03-09T17:46:45.754831"
    },
    {
      "symbol": "LLY",
      "name": "Eli Lilly and Company",
      "sector": "Healthcare",
      "industry": "Drug Manufacturers - General",
      "price": 994.93,
      "market_cap": 890485473280,
      "fundamentals": {
        "trailing_pe": 43.3,
        "forward_pe": 23.71,
        "pb_ratio": 33.55,
        "ps_ratio": 13.66,
        "ev_ebitda": 29.07,
        "earnings_yield": 2.31,
        "revenue_growth": 42.6,
        "earnings_growth": 51.4,
        "growth_tier": "hypergrowth"
      },
      "technicals": {
        "sma_50": 1044.4,
        "sma_200": 879.63,
        "rsi": 40.98,
        "week_52_high": 1133.95,
        "week_52_low": 623.78,
        "bollinger_position": 15.49,
        "price_vs_sma50": -4.74,
        "price_vs_sma200": 13.11
      },
      "scores": {
        "per_score": 34.0,
        "pbr_score": 0,
        "psr_score": 10,
        "ev_ebitda_score": 10,
        "earnings_yield_score": 0,
        "fundamental_score": 13.7,
        "technical_score": 62.18,
        "value_score": 28.24
      },
      "grade": "D",
      "recommendation": "Avoid",
      "fetched_at": "2026-03-09T17:46:47.672853"
    },
    {
      "symbol": "GE",
      "name": "GE Aerospace",
      "sector": "Industrials",
      "industry": "Aerospace & Defense",
      "price": 315.38,
      "market_cap": 332667224064,
      "fundamentals": {
        "trailing_pe": 39.18,
        "forward_pe": 36.87,
        "pb_ratio": 17.71,
        "ps_ratio": 7.25,
        "ev_ebitda": 32.58,
        "earnings_yield": 2.55,
        "revenue_growth": 17.6,
        "earnings_growth": 37.4,
        "growth_tier": "hypergrowth"
      },
      "technicals": {
        "sma_50": 319.61,
        "sma_200": 288.48,
        "rsi": 42.54,
        "week_52_high": 348.48,
        "week_52_low": 159.36,
        "bollinger_position": 18.12,
        "price_vs_sma50": -1.32,
        "price_vs_sma200": 9.33
      },
      "scores": {
        "per_score": 20.0,
        "pbr_score": 10,
        "psr_score": 20,
        "ev_ebitda_score": 10,
        "earnings_yield_score": 20,
        "fundamental_score": 16.0,
        "technical_score": 55.2,
        "value_score": 27.76
      },
      "grade": "D",
      "recommendation": "Avoid",
      "fetched_at": "2026-03-09T17:46:53.307962"
    },
    {
      "symbol": "COST",
      "name": "Costco Wholesale Corporation",
      "sector": "Consumer Defensive",
      "industry": "Discount Stores",
      "price": 1002.52,
      "market_cap": 445076471808,
      "fundamentals": {
        "trailing_pe": 53.73,
        "forward_pe": 44.74,
        "pb_ratio": 13.86,
        "ps_ratio": 1.55,
        "ev_ebitda": 32.15,
        "earnings_yield": 1.86,
        "revenue_growth": 9.2,
        "earnings_growth": 13.9,
        "growth_tier": "moderate_growth"
      },
      "technicals": {
        "sma_50": 959.71,
        "sma_200": 949.79,
        "rsi": 46.44,
        "week_52_high": 1067.08,
        "week_52_low": 844.06,
        "bollinger_position": 63.42,
        "price_vs_sma50": 4.46,
        "price_vs_sma200": 5.55
      },
      "scores": {
        "per_score": 10.0,
        "pbr_score": 10,
        "psr_score": 80,
        "ev_ebitda_score": 10,
        "earnings_yield_score": 0,
        "fundamental_score": 19.0,
        "technical_score": 47.76,
        "value_score": 27.63
      },
      "grade": "D",
      "recommendation": "Avoid",
      "fetched_at": "2026-03-09T17:46:50.004856"
    },
    {
      "symbol": "RTX",
      "name": "RTX Corporation",
      "sector": "Industrials",
      "industry": "Aerospace & Defense",
      "price": 208.69,
      "market_cap": 280121999360,
      "fundamentals": {
        "trailing_pe": 42.16,
        "forward_pe": 27.79,
        "pb_ratio": 4.29,
        "ps_ratio": 3.16,
        "ev_ebitda": 21.44,
        "earnings_yield": 2.37,
        "revenue_growth": 12.1,
        "earnings_growth": 8.3,
        "growth_tier": "moderate_growth"
      },
      "technicals": {
        "sma_50": 196.93,
        "sma_200": 167.84,
        "rsi": 56.23,
        "week_52_high": 214.5,
        "week_52_low": 112.27,
        "bollinger_position": 80.98,
        "price_vs_sma50": 5.97,
        "price_vs_sma200": 24.34
      },
      "scores": {
        "per_score": 30.0,
        "pbr_score": 20,
        "psr_score": 40,
        "ev_ebitda_score": 10,
        "earnings_yield_score": 0,
        "fundamental_score": 21.0,
        "technical_score": 41.83,
        "value_score": 27.25
      },
      "grade": "D",
      "recommendation": "Avoid",
      "fetched_at": "2026-03-09T17:46:55.000649"
    },
    {
      "symbol": "MA",
      "name": "Mastercard Incorporated",
      "sector": "Financial Services",
      "industry": "Credit Services",
      "price": 509.82,
      "market_cap": 454982598656,
      "fundamentals": {
        "trailing_pe": 30.88,
        "forward_pe": 22.53,
        "pb_ratio": 58.91,
        "ps_ratio": 13.88,
        "ev_ebitda": 23.11,
        "earnings_yield": 3.24,
        "revenue_growth": 17.6,
        "earnings_growth": 24.2,
        "growth_tier": "high_growth"
      },
      "technicals": {
        "sma_50": 540.19,
        "sma_200": 559.02,
        "rsi": 43.73,
        "week_52_high": 601.77,
        "week_52_low": 465.59,
        "bollinger_position": 25.32,
        "price_vs_sma50": -5.62,
        "price_vs_sma200": -8.8
      },
      "scores": {
        "per_score": 32.0,
        "pbr_score": 0,
        "psr_score": 10,
        "ev_ebitda_score": 10,
        "earnings_yield_score": 20,
        "fundamental_score": 16.1,
        "technical_score": 51.66,
        "value_score": 26.77
      },
      "grade": "D",
      "recommendation": "Avoid",
      "fetched_at": "2026-03-09T17:46:43.051062"
    },
    {
      "symbol": "SBUX",
      "name": "Starbucks Corporation",
      "sector": "Consumer Cyclical",
      "industry": "Restaurants",
      "price": 97.9,
      "market_cap": 111526076416,
      "fundamentals": {
        "trailing_pe": 81.58,
        "forward_pe": 33.15,
        "pb_ratio": -13.29,
        "ps_ratio": 2.96,
        "ev_ebitda": 25.42,
        "earnings_yield": 1.23,
        "revenue_growth": 5.5,
        "earnings_growth": -62.5,
        "growth_tier": "declining"
      },
      "technicals": {
        "sma_50": 93.24,
        "sma_200": 87.92,
        "rsi": 59.74,
        "week_52_high": 106.0,
        "week_52_low": 75.5,
        "bollinger_position": 67.02,
        "price_vs_sma50": 5.0,
        "price_vs_sma200": 11.36
      },
      "scores": {
        "per_score": 6.0,
        "pbr_score": 0,
        "psr_score": 60,
        "ev_ebitda_score": 10,
        "earnings_yield_score": 0,
        "fundamental_score": 12.8,
        "technical_score": 49.01,
        "value_score": 23.66
      },
      "grade": "D",
      "recommendation": "Avoid",
      "fetched_at": "2026-03-09T17:46:51.539557"
    },
    {
      "symbol": "TSLA",
      "name": "Tesla, Inc.",
      "sector": "Consumer Cyclical",
      "industry": "Auto Manufacturers",
      "price": 389.19,
      "market_cap": 1460559151104,
      "fundamentals": {
        "trailing_pe": 363.77,
        "forward_pe": 138.49,
        "pb_ratio": 17.78,
        "ps_ratio": 15.4,
        "ev_ebitda": 139.02,
        "earnings_yield": 0.27,
        "revenue_growth": -3.1,
        "earnings_growth": -60.6,
        "growth_tier": "declining"
      },
      "technicals": {
        "sma_50": 426.08,
        "sma_200": 392.33,
        "rsi": 37.76,
        "week_52_high": 498.83,
        "week_52_low": 214.25,
        "bollinger_position": 0,
        "price_vs_sma50": -8.66,
        "price_vs_sma200": -0.8
      },
      "scores": {
        "per_score": 0.0,
        "pbr_score": 10,
        "psr_score": 10,
        "ev_ebitda_score": 0,
        "earnings_yield_score": 0,
        "fundamental_score": 3.5,
        "technical_score": 64.65,
        "value_score": 21.84
      },
      "grade": "D",
      "recommendation": "Avoid",
      "fetched_at": "2026-03-09T17:46:39.834800"
    }
  ],
  "statistics": {
    "total_analyzed": 60,
    "successful": 60,
    "failed": 0,
    "avg_score": 41.53,
    "max_score": 67.77,
    "min_score": 21.84,
    "grade_distribution": {
      "A+": 0,
      "A": 0,
      "B+": 6,
      "B": 10,
      "C": 14,
      "D": 30
    }
  },
  "failed_symbols": [],
  "last_updated": "2026-03-09T17:47:00.499871",
  "screening_criteria": {
    "min_score": 0,
    "symbols_count": 60
  }
}